Workbook
Name Slicer_country: #N/A
Name Slicer_gender: #N/A
Name Slicer_is_active_member: #N/A
Name Slicer_num_of_products: #N/A

Sheet 01 - Raw data
A1: Row_Number | B1: Customer_ID | C1: Last_Name | D1: Credit Score | E1: Country | F1: Gender | G1: Age | H1: Tenure | I1: Balance | J1: NumOfProducts | K1: HasCrCard? | L1: IsActiveMember | M1: Estimated Salary | N1: ExitedFromBank?
A2: 1 | B2: 15634602 | C2: Hargrave | D2: 619 | E2: France | F2: Female | G2: 42 | H2: 2 | I2: 0 | J2: 1 | K2: 1 | L2: 1 | M2: 101348.88 | N2: 1
A3: 2 | B3: 15647311 | C3: Hill | D3: 608 | E3: Spain | F3: Female | G3: 41 | H3: 1 | I3: 83807.86 | J3: 1 | K3: 0 | L3: 1 | M3: 112542.58 | N3: 0
A4: 3 | B4: 15619304 | C4: Onio | D4: 502 | E4: France | F4: Female | G4: 42 | H4: 8 | I4: 159660.8 | J4: 3 | K4: 1 | L4: 0 | M4: 113931.57 | N4: 1
A5: 4 | B5: 15701354 | C5: Boni | D5: 699 | E5: France | F5: Female | G5: 39 | H5: 1 | I5: 0 | J5: 2 | K5: 0 | L5: 0 | M5: 93826.63 | N5: 0
A6: 5 | B6: 15737888 | C6: Mitchell | D6: 850 | E6: Spain | F6: Female | G6: 43 | H6: 2 | I6: 125510.82 | J6: 1 | K6: 1 | L6: 1 | M6: 79084.1 | N6: 0
A7: 6 | B7: 15574012 | C7: Chu | D7: 645 | E7: Spain | F7: Male | G7: 44 | H7: 8 | I7: 113755.78 | J7: 2 | K7: 1 | L7: 0 | M7: 149756.71 | N7: 1
A8: 7 | B8: 15592531 | C8: Bartlett | D8: 822 | E8: France | F8: Male | G8: 50 | H8: 7 | I8: 0 | J8: 2 | K8: 1 | L8: 1 | M8: 10062.8 | N8: 0
A9: 8 | B9: 15656148 | C9: Obinna | D9: 376 | E9: Germany | F9: Female | G9: 29 | H9: 4 | I9: 115046.74 | J9: 4 | K9: 1 | L9: 0 | M9: 119346.88 | N9: 1
A10: 9 | B10: 15792365 | C10: He | D10: 501 | E10: France | F10: Male | G10: 44 | H10: 4 | I10: 142051.07 | J10: 2 | K10: 0 | L10: 1 | M10: 74940.5 | N10: 0
A11: 10 | B11: 15592389 | C11: H? | D11: 684 | E11: France | F11: Male | G11: 27 | H11: 2 | I11: 134603.88 | J11: 1 | K11: 1 | L11: 1 | M11: 71725.73 | N11: 0
A12: 11 | B12: 15767821 | C12: Bearce | D12: 528 | E12: France | F12: Male | G12: 31 | H12: 6 | I12: 102016.72 | J12: 2 | K12: 0 | L12: 0 | M12: 80181.12 | N12: 0
A13: 12 | B13: 15737173 | C13: Andrews | D13: 497 | E13: Spain | F13: NULL | G13: 24 | H13: 3 | I13: 0 | J13: 2 | K13: 1 | L13: 0 | M13: 76390.01 | N13: 0
... A22: 21 | B22: 15577657 | C22: McDonald | D22: 732 | E22: FR | F22: Male | G22: 41 | H22: 8 | I22: 0 | J22: 2 | K22: 1 | L22: 1 | M22: 170886.17 | N22: 0
A23: 22 | B23: 15597945 | C23: Dellucci | D23: 636 | E23: Spain | F23: Female | G23: 32 | H23: 8 | I23: 0 | J23: 2 | K23: 1 | L23: 0 | N23: 0
A24: 23 | B24: 15699309 | C24: Gerasimov | D24: 510 | E24: Spain | F24: Female | G24: NULL | H24: 4 | I24: 0 | J24: 1 | K24: 1 | L24: 0 | M24: 118913.53 | N24: 1
A25: 24 | B25: 15725737 | C25: Mosman | D25: 669 | E25: FR | F25: Male | G25: 46 | H25: 3 | I25: 0 | J25: 2 | K25: 0 | L25: 1 | M25: 8487.75 | N25: 0
A26: 25 | B26: 15625047 | C26: Yen | D26: 846 | E26: FR | F26: Female | G26: 38 | H26: 5 | I26: 0 | J26: 1 | K26: 1 | L26: 1 | M26: 187616.16 | N26: 0
A27: 26 | B27: 15738191 | C27: Maclean | D27: 577 | E27: FR | F27: Male | G27: 25 | H27: 3 | I27: 0 | J27: 2 | K27: 0 | L27: 1 | M27: 124508.29 | N27: 0
A28: 27 | B28: 15736816 | C28: Young | D28: 756 | E28: Germany | F28: Male | G28: 36 | H28: 2 | I28: 136815.64 | J28: 1 | K28: 1 | L28: 1 | M28: 170041.95 | N28: 0
A29: 28 | B29: 15700772 | C29: Nebechi | D29: 571 | E29: FR | F29: Male | G29: 44 | H29: 9 | I29: 0 | J29: 2 | K29: 0 | L29: 0 | M29: 38433.35 | N29: 0
A30: 29 | B30: 15728693 | C30: McWilliams | D30: 574 | E30: Germany | F30: Female | G30: 43 | H30: 3 | I30: 141349.43 | J30: 1 | K30: 1 | L30: 1 | M30: 100187.43 | N30: 0
A31: 30 | B31: 15656300 | C31: Lucciano | D31: 411 | E31: FR | F31: Male | G31: 29 | H31: 0 | I31: 59697.17 | J31: 2 | K31: 1 | L31: 1 | M31: 53483.21 | N31: 0
A32: 31 | B32: 15589475 | C32: Azikiwe | D32: 591 | E32: Spain | F32: Female | G32: 39 | H32: 3 | I32: 0 | J32: 3 | K32: 1 | L32: 0 | M32: 140469.38 | N32: 1
A33: 32 | B33: 15706552 | C33: Odinakachukwu | D33: 533 | E33: FR | F33: Male | G33: 36 | H33: 7 | I33: 85311.7 | J33: 1 | K33: 0 | L33: 1 | M33: 156731.91 | N33: 0
A34: 33 | B34: 15750181 | C34: Sanderson | D34: 553 | E34: Germany | F34: Male | G34: 41 | H34: 9 | I34: 110112.54 | J34: 2 | K34: 0 | L34: 0 | M34: 81898.81 | N34: 0
A35: 34 | B35: 15659428 | C35: Maggard | D35: 520 | E35: Spain | F35: Female | G35: 42 | H35: 6 | I35: 0 | J35: 2 | K35: 1 | L35: 1 | M35: 34410.55 | N35: 0
A36: 35 | B36: 15732963 | C36: Clements | D36: 722 | E36: Spain | F36: Female | G36: 29 | H36: 9 | I36: 0 | J36: 2 | K36: 1 | L36: 1 | M36: 142033.07 | N36: 0
... A205: 204 | B205: 15727868 | C205: Onuora | D205: 711 | E205: FR | F205: Female | G205: 38 | H205: 2 | I205: 129022.06 | J205: 2 | K205: 1 | L205: 1 | M205: 14374.86 | N205: 1
A206: 205 | B206: 15627801 | C206: Ginikanwa | E206: ES | F206: Male | G206: 33 | H206: 3 | I206: 176666.62 | J206: 1 | K206: 1 | L206: 0 | M206: 94670.77 | N206: 0
A207: 206 | B207: 15773039 | C207: Ku | D207: 550 | E207: FR | F207: Male | G207: 37 | H207: 3 | I207: 0 | J207: 1 | K207: 1 | L207: 1 | M207: 179670.31 | N207: 0
A208: 207 | B208: 15755262 | C208: McDonald | D208: 608 | E208: ES | F208: Female | G208: 41 | H208: 3 | I208: 89763.84 | J208: 1 | K208: 0 | L208: 0 | M208: 199304.74 | N208: 1
A209: 208 | B209: 15679531 | C209: Collins | D209: 618 | E209: FR | F209: Male | G209: 34 | H209: 5 | I209: 134954.53 | J209: 1 | K209: 1 | L209: 1 | M209: 151954.39 | N209: 0
A210: 209 | B210: 15684181 | C210: Hackett | D210: 643 | E210: FR | F210: Male | G210: 45 | H210: 5 | I210: 0 | J210: 1 | K210: 1 | L210: 0 | M210: 142513.5 | N210: 1
A211: 210 | B211: 15612087 | C211: Dike | D211: 671 | E211: FR | F211: Male | G211: 45 | H211: 2 | I211: 106376.85 | J211: 1 | K211: 0 | L211: 1 | M211: 158264.62 | N211: 0
A212: 211 | B212: 15752047 | D212: 689 | E212: DE | F212: Male | G212: 33 | H212: 2 | I212: 161814.64 | J212: 2 | K212: 1 | L212: 0 | M212: 169381.9 | N212: 0
A213: 212 | B213: 15624592 | C213: Tan | D213: 603 | E213: FR | F213: Male | G213: 31 | H213: 8 | I213: 0 | J213: 2 | K213: 1 | L213: 1 | M213: 169915.02 | N213: 0
A214: 213 | B214: 15573152 | C214: Glassman | D214: 620 | E214: FR | F214: Female | G214: 41 | H214: 9 | I214: 0 | J214: 2 | K214: 0 | L214: 0 | M214: 88852.47 | N214: 0
A215: 214 | B215: 15594917 | C215: Miller | D215: 676 | E215: FR | F215: Female | G215: 34 | H215: 1 | I215: 63095.01 | J215: 1 | K215: 1 | L215: 1 | M215: 40645.81 | N215: 0
A216: 215 | B216: 15785542 | C216: Kornilova | E216: DE | F216: Male | G216: 26 | H216: 4 | I216: 118287.01 | J216: 2 | K216: 0 | L216: 0 | M216: NULL | N216: 0
A217: 216 | B217: 15723488 | C217: Watson | D217: 668 | E217: DE | F217: Male | G217: 47 | H217: 7 | I217: 106854.21 | J217: 1 | K217: 0 | L217: 1 | M217: 157959.02 | N217: 1
A218: 217 | B218: 15680920 | C218: Marchesi | D218: 695 | E218: FR | F218: Male | G218: 46 | H218: 7 | I218: 49512.55 | J218: 1 | K218: 1 | L218: 0 | M218: 133007.34 | N218: 0
A219: 218 | B219: 15786308 | C219: Millar | D219: 730 | E219: ES | F219: Female | G219: 33 | H219: 9 | I219: 0 | J219: 2 | K219: 0 | L219: 0 | M219: 176576.62 | N219: 0
A220: 219 | B220: 15659366 | C220: Shih | D220: 807 | E220: FR | F220: Male | G220: 43 | H220: 1 | I220: 105799.32 | J220: 2 | K220: 1 | L220: 0 | M220: 34888.04 | N220: 1
A221: 220 | B221: 15774854 | C221: Fuller | D221: 592 | E221: FR | F221: Male | G221: 54 | H221: 8 | I221: 0 | J221: 1 | K221: 1 | L221: 1 | M221: 28737.71 | N221: 1
A222: 221 | B222: 15725311 | C222: Hay | D222: 726 | E222: FR | F222: Female | G222: 31 | H222: 9 | I222: 114722.05 | J222: 2 | K222: 1 | L222: 1 | M222: 98178.57 | N222: 0
A223: 222 | B223: 15787155 | C223: Yang | D223: 514 | E223: ES | F223: Male | G223: 30 | H223: 7 | I223: 0 | J223: 1 | K223: 0 | L223: 1 | M223: 125010.24 | N223: 0
A224: 223 | B224: 15727829 | C224: McIntyre | D224: 567 | E224: FR | F224: Male | G224: 42 | H224: 2 | I224: 0 | J224: 2 | K224: 1 | L224: 1 | M224: 167984.61 | N224: 0
A225: 224 | B225: 15733247 | C225: Stevenson | D225: 850 | E225: FR | F225: Male | G225: 33 | H225: 10 | I225: 0 | J225: 1 | K225: 1 | L225: 0 | M225: 4861.72 | N225: 1
A226: 225 | B226: 15568748 | C226: Poole | D226: 671 | E226: DE | F226: Male | G226: 45 | H226: 6 | I226: 99564.22 | J226: 1 | K226: 1 | L226: 1 | M226: 108872.45 | N226: 1
A227: 226 | B227: 15699029 | C227: Bagley | D227: 670 | E227: FR | F227: Male | G227: 37 | H227: 4 | I227: 170557.91 | J227: 2 | K227: 1 | L227: 0 | M227: 198252.88 | N227: 0
A228: 227 | B228: 15774393 | C228: Ch'ien | D228: 694 | E228: FR | F228: Female | G228: 30 | H228: 9 | I228: 0 | J228: 2 | K228: 1 | L228: 1 | M228: 26960.31 | N228: 0
... A977: 976 | B977: 15685357 | C977: Wright | D977: 750 | E977: ES | F977: Female | G977: 36 | H977: 8 | I977: 112940.07 | J977: 1 | K977: 0 | L977: 1 | M977: 9855.81 | N977: 0
A978: 977 | B978: 15570060 | C978: Palerma | E978: France | F978: Female | G978: 43 | H978: 8 | I978: 132558.26 | J978: 1 | K978: 1 | L978: 0 | M978: 67046.83 | N978: 1
A979: 978 | B979: 15582616 | C979: Y?an | D979: 520 | E979: France | F979: Female | G979: 38 | H979: 4 | I979: 0 | J979: 2 | K979: 1 | L979: 0 | M979: 56388.63 | N979: 0
A980: 979 | B980: 15799515 | C980: Wei | D980: 652 | E980: France | F980: Female | G980: 48 | H980: 8 | I980: 133297.24 | J980: 1 | K980: 1 | L980: 0 | M980: 77764.37 | N980: 0
A981: 980 | B981: 15642937 | C981: Padovesi | D981: 550 | E981: France | F981: Female | G981: 46 | H981: 7 | I981: 0 | J981: 2 | K981: 1 | L981: 0 | M981: 130590.35 | N981: 0
A982: 981 | B982: 15624729 | C982: Tsao | D982: 594 | E982: France | F982: Male | G982: 27 | H982: 0 | I982: 197041.8 | J982: 1 | K982: 0 | L982: 0 | M982: 151912.49 | N982: 0
A983: 982 | B983: 15566156 | C983: Franklin | D983: 749 | E983: Germany | F983: Female | G983: 44 | H983: 0 | I983: 71497.79 | J983: 2 | K983: 0 | L983: 0 | M983: 151083.8 | N983: 0
A984: 983 | B984: 15792360 | C984: Clark | D984: 668 | E984: France | F984: Male | G984: 32 | H984: 7 | I984: 0 | J984: 2 | K984: 1 | L984: 1 | M984: 777.37 | N984: 0
A985: 984 | B985: 15807008 | C985: McGregor | D985: 614 | E985: Germany | F985: Female | G985: 35 | H985: 6 | I985: 128100.28 | J985: 1 | K985: 0 | L985: 0 | M985: 69454.24 | N985: 1
A986: 985 | B986: 15704770 | C986: Pan | D986: 773 | E986: France | F986: Male | G986: 25 | H986: 1 | I986: 124532.78 | J986: 2 | K986: 0 | L986: 1 | M986: 11723.57 | N986: 0
A987: 986 | B987: 15756475 | C987: Kenniff | D987: 551 | E987: Germany | F987: Male | G987: 31 | H987: 9 | I987: 82293.82 | J987: 2 | K987: 1 | L987: 1 | M987: 91565.25 | N987: 0
A988: 987 | B988: 15655339 | C988: Spencer | D988: 566 | E988: France | F988: Male | G988: 36 | H988: 1 | I988: 142120.91 | J988: 1 | K988: 1 | L988: 0 | M988: 79616.37 | N988: 0
A989: 988 | B989: 15613749 | C989: Lees | D989: 569 | E989: ES | F989: Male | G989: 34 | H989: 0 | I989: 151839.26 | J989: 1 | K989: 1 | L989: 0 | M989: 102299.81 | N989: 1
A990: 989 | B990: 15664521 | C990: David | D990: 659 | E990: ES | F990: Male | G990: 31 | H990: 7 | I990: 149620.88 | J990: 2 | K990: 1 | L990: 1 | M990: 104533.51 | N990: 0
... A992: 991 | B992: 15745527 | C992: Burke | D992: 655 | E992: France | F992: Male | G992: 37 | H992: 5 | I992: 93147 | J992: 2 | K992: 1 | L992: 0 | M992: 66214.13 | N992: 0

Sheet 02 - Data Profiling
B2: Variables and Data Types
C5: Data Types
B6: Variables | C6: Time-variant/-invariant | D6: Structured/Unstructured | E6: Qualitative/Quantitative | F6: Qualitative: Nominal/Ordinal Quantitative: Discrete/Continuous
B7: Row_Number | C7: Time-invariant | D7: Structured | E7: Qualitative | F7: Nominal
B8: Customer_ID | C8: Time-invariant | D8: Structured | E8: Qualitative | F8: Nominal
B9: Last_Name | C9: Time-invariant | D9: Structured | E9: Qualitative | F9: Nominal
B10: Credit Score | C10: Time-invariant | D10: Structured | E10: Quantitative | F10: Discrete
B11: Country | C11: Time-invariant | D11: Structured | E11: Qualitative | F11: Nominal
B12: Gender | C12: Time-invariant | D12: Structured | E12: Qualitative | F12: Nominal
B13: Age | C13: Time-invariant | D13: Structured | E13: Quantitative | F13: Discrete
B14: Tenure | C14: Time-invariant | D14: Structured | E14: Quantitative | F14: Discrete
B15: Balance | C15: Time-variant | D15: Structured | E15: Quantitative | F15: Continuous
B16: NumOfProducts | C16: Time-variant | D16: Structured | E16: Quantitative | F16: Discrete
B17: HasCrCard? | C17: Time-invariant | D17: Structured | E17: Qualitative | F17: Binary
... B20: ExitedFromBank? | C20: Time-invariant | D20: Structured | E20: Qualitative | F20: Binary

Sheet 03 - Data Integrity
B2: Data Accuracy
B4: (Numeric Columns) | C4: Minimum | D4: Maximum | E4: Mean | F4: Notes
B5: Credit Score | C5: =+MIN('01 - Raw data'!D2:D992) -> 376 | D5: =+MAX('01 - Raw data'!D2:D992) -> 850 | E5: =+AVERAGE('01 - Raw data'!D2:D992) -> 648.51215 | F5: -
B6: Age | C6: =MIN('01 - Raw data'!G2:G992) -> 2 | D6: =MAX('01 - Raw data'!G2:G992) -> 82 | E6: =AVERAGE('01 - Raw data'!G2:G992) -> 38.684848 | F6: Minimum age should be 18.
B7: Tenure | C7: =MIN('01 - Raw data'!H2:H992) -> 0 | D7: =MAX('01 - Raw data'!H2:H992) -> 10 | E7: =AVERAGE('01 - Raw data'!H2:H992) -> 5.0665994 | F7: Tenure 0 should mean new customers.
B8: Balance | C8: =MIN('01 - Raw data'!I2:I992) -> 0 | D8: =MAX('01 - Raw data'!I2:I992) -> 213146.2 | E8: =AVERAGE('01 - Raw data'!I2:I992) -> 78002.718 | F8: Balance 0 could mean missing data or a real empty account.
B9: NumOfProducts | C9: =MIN('01 - Raw data'!J2:J992) -> 1 | D9: =MAX('01 - Raw data'!J2:J992) -> 4 | E9: =AVERAGE('01 - Raw data'!J2:J992) -> 1.5227043 | F9: -
B10: Estimated Salary | C10: =MIN('01 - Raw data'!M2:M992) -> 371.05 | D10: =MAX('01 - Raw data'!M2:M992) -> 199725.39 | E10: =AVERAGE('01 - Raw data'!M2:M992) -> 98574.543 | F10: -
B13: Data Consistency
B15: Variables | C15: Count | D15: Notes
B16: Row_Number | C16: 991 | D16: -
B17: Customer_ID | C17: 991 | D17: -
B18: Last_Name | C18: 210 | D18: Blank values
B19: Credit Score | C19: 988 | D19: Blank values
B20: Country | C20: 991 | D20: Name varieties
B21: Gender | C21: 991 | D21: Name varieties and 1 null
B22: Age | C22: 991 | D22: 1 null value
B23: Tenure | C23: 991 | D23: -
B24: Balance | C24: 991 | D24: -
B25: NumOfProducts | C25: 991 | D25: -
B26: HasCrCard? | C26: 991 | D26: -
B27: IsActiveMember | C27: 991 | D27: -
... B29: ExitedFromBank? | C29: 991 | D29: -
B31: (Frequency Tables)
B33: Row Labels | C33: Count of Row_Number | E33: Row Labels | F33: Count of Customer_ID | H33: Row Labels | I33: Count of Last_Name | K33: Row Labels | L33: Count of Credit Score | N33: Row Labels | O33: Count of Country | Q33: Row Labels | R33: Count of Gender | T33: Row Labels | U33: Count of Age | W33: Row Labels | X33: Count of Tenure | Z33: Row Labels | AA33: Count of Balance | AC33: Row Labels | AD33: Count of NumOfProducts | AF33: Row Labels | AG33: Count of HasCrCard? | AI33: Row Labels | AJ33: Count of IsActiveMember | AL33: Row Labels | AM33: Count of Estimated Salary | AO33: Row Labels | AP33: Count of ExitedFromBank?
B34: 1 | C34: 1 | E34: 15566091 | F34: 1 | H34: Sun | I34: 1 | K34: 376 | L34: 2 | N34: DE | O34: 23 | Q34: F | R34: 19 | T34: 2 | U34: 11 | W34: 0 | X34: 38 | Z34: 0 | AA34: 349 | AC34: 1 | AD34: 510 | AF34: 0 | AG34: 291 | AI34: 0 | AJ34: 488 | AL34: 371.05 | AM34: 1 | AO34: 0 | AP34: 787
B35: 2 | C35: 1 | E35: 15566111 | F35: 1 | H35: Alekseeva | I35: 1 | K35: 411 | L35: 1 | N35: ES | O35: 118 | Q35: Female | R35: 443 | T35: 18 | U35: 1 | W35: 1 | X35: 103 | Z35: 34013.63 | AA35: 1 | AC35: 2 | AD35: 446 | AF35: 1 | AG35: 700 | AI35: 1 | AJ35: 503 | AL35: 417.41 | AM35: 1 | AO35: 1 | AP35: 204
B36: 3 | C36: 1 | E36: 15566156 | F36: 1 | H36: Aleshire | I36: 1 | K36: 413 | L36: 1 | N36: FR | O36: 244 | Q36: M | R36: 49 | T36: 19 | U36: 2 | W36: 2 | X36: 110 | Z36: 37266.67 | AA36: 1 | AC36: 3 | AD36: 33 | AF36: Grand Total | AG36: 991 | AI36: Grand Total | AJ36: 991 | AL36: 447.73 | AM36: 1 | AO36: Grand Total | AP36: 991
B37: 4 | C37: 1 | E37: 15566292 | F37: 1 | H37: Alexeeva | I37: 1 | K37: 416 | L37: 2 | N37: France | O37: 236 | Q37: Male | R37: 479 | T37: 20 | U37: 1 | W37: 3 | X37: 101 | Z37: 40105.51 | AA37: 1 | AC37: 4 | AD37: 2 | AL37: 600.36 | AM37: 1
B38: 5 | C38: 1 | E38: 15566594 | F38: 1 | H38: Allard | I38: 1 | K38: 417 | L38: 1 | N38: Germany | O38: 234 | Q38: NULL | R38: 1 | T38: 21 | U38: 6 | W38: 4 | X38: 86 | Z38: 40685.92 | AA38: 1 | AC38: Grand Total | AD38: 991 | AL38: 705.18 | AM38: 1
B39: 6 | C39: 1 | E39: 15567367 | F39: 1 | H39: Andrews | I39: 1 | K39: 421 | L39: 1 | N39: Spain | O39: 136 | Q39: Grand Total | R39: 991 | T39: 22 | U39: 7 | W39: 5 | X39: 100 | Z39: 40915.55 | AA39: 1 | AL39: 777.37 | AM39: 1
B40: 7 | C40: 1 | E40: 15567446 | F40: 1 | H40: Armstrong | I40: 1 | K40: 427 | L40: 1 | N40: Grand Total | O40: 991 | T40: 23 | U40: 4 | W40: 6 | X40: 94 | Z40: 42157.08 | AA40: 1 | AL40: 823.36 | AM40: 1
B41: 8 | C41: 1 | E41: 15567832 | F41: 1 | H41: Arthur | I41: 1 | K41: 429 | L41: 1 | T41: 24 | U41: 15 | W41: 7 | X41: 93 | Z41: 45144.43 | AA41: 1 | AL41: 878.87 | AM41: 1
B42: 9 | C42: 1 | E42: 15568240 | F42: 1 | H42: Ashbolt | I42: 1 | K42: 432 | L42: 1 | T42: 25 | U42: 22 | W42: 8 | X42: 108 | Z42: 47134.75 | AA42: 1 | AL42: 1002.39 | AM42: 1
B43: 10 | C43: 1 | E43: 15568506 | F43: 1 | H43: Azikiwe | I43: 1 | K43: 435 | L43: 2 | T43: 26 | U43: 22 | W43: 9 | X43: 108 | Z43: 49512.55 | AA43: 1 | AL43: 1299.75 | AM43: 1
B44: 11 | C44: 1 | E44: 15568595 | F44: 1 | H44: Ballard | I44: 1 | K44: 438 | L44: 3 | T44: 27 | U44: 16 | W44: 10 | X44: 50 | Z44: 52436.2 | AA44: 1 | AL44: 1643.11 | AM44: 1
B45: 12 | C45: 1 | E45: 15568748 | F45: 1 | H45: Bartlett | I45: 1 | K45: 439 | L45: 1 | T45: 28 | U45: 21 | W45: Grand Total | X45: 991 | Z45: 54503.55 | AA45: 1 | AL45: 1907.66 | AM45: 1
B46: 13 | C46: 1 | E46: 15568982 | F46: 1 | H46: Bearce | I46: 1 | K46: 443 | L46: 2 | T46: 29 | U46: 32 | Z46: 54901.01 | AA46: 1 | AL46: 2010.98 | AM46: 1
B47: 14 | C47: 1 | E47: 15569590 | F47: 1 | H47: Beit | I47: 1 | K47: 445 | L47: 1 | T47: 30 | U47: 32 | Z47: 56084.69 | AA47: 1 | AL47: 2079.2 | AM47: 1
B48: 15 | C48: 1 | E48: 15569807 | F48: 1 | H48: Bennelong | I48: 1 | K48: 450 | L48: 1 | T48: 31 | U48: 43 | Z48: 56214.85 | AA48: 1 | AL48: 2319.96 | AM48: 1
B49: 16 | C49: 1 | E49: 15570060 | F49: 1 | H49: Bianchi | I49: 1 | K49: 456 | L49: 1 | T49: 32 | U49: 37 | Z49: 57017.06 | AA49: 1 | AL49: 2383.59 | AM49: 1
B50: 17 | C50: 1 | E50: 15570134 | F50: 1 | H50: Boni | I50: 1 | K50: 459 | L50: 2 | T50: 33 | U50: 34 | Z50: 57929.81 | AA50: 1 | AL50: 3710.34 | AM50: 1
B51: 18 | C51: 1 | E51: 15571002 | F51: 1 | H51: Bradley | I51: 1 | K51: 460 | L51: 2 | T51: 34 | U51: 46 | Z51: 58469.37 | AA51: 1 | AL51: 3937.37 | AM51: 1
B52: 19 | C52: 1 | E52: 15571221 | F52: 1 | H52: Brownless | I52: 1 | K52: 461 | L52: 1 | T52: 35 | U52: 55 | Z52: 58629.97 | AA52: 1 | AL52: 4389.4 | AM52: 1
B53: 20 | C53: 1 | E53: 15571816 | F53: 1 | H53: Buccho | I53: 1 | K53: 464 | L53: 2 | T53: 36 | U53: 59 | Z53: 58641.43 | AA53: 1 | AL53: 4400.32 | AM53: 1
B54: 21 | C54: 1 | E54: 15571928 | F54: 1 | H54: Buley | I54: 1 | K54: 465 | L54: 1 | T54: 37 | U54: 45 | Z54: 59408.63 | AA54: 1 | AL54: 4861.72 | AM54: 1
B55: 22 | C55: 1 | E55: 15571973 | F55: 1 | H55: Bushell | I55: 1 | K55: 468 | L55: 3 | T55: 38 | U55: 42 | Z55: 59697.17 | AA55: 1 | AL55: 5097.67 | AM55: 1
B56: 23 | C56: 1 | E56: 15572265 | F56: 1 | H56: Calabresi | I56: 1 | K56: 472 | L56: 1 | T56: 39 | U56: 41 | Z56: 61710.44 | AA56: 1 | AL56: 5472.7 | AM56: 1
B57: 24 | C57: 1 | E57: 15573112 | F57: 1 | H57: Cameron | I57: 2 | K57: 474 | L57: 2 | T57: 40 | U57: 32 | Z57: 61825.5 | AA57: 1 | AL57: 5597.94 | AM57: 1
... B94: 61 | C94: 1 | E94: 15583725 | F94: 1 | H94: Fu | I94: 2 | K94: 518 | L94: 1 | T94: 82 | U94: 1 | Z94: 77780.29 | AA94: 1 | AL94: 10553.31 | AM94: 1
B95: 62 | C95: 1 | E95: 15584091 | F95: 1 | H95: Fuller | I95: 1 | K95: 519 | L95: 3 | T95: NULL | U95: 1 | Z95: 77846.9 | AA95: 1 | AL95: 10598.29 | AM95: 1
B96: 63 | C96: 1 | E96: 15584518 | F96: 1 | H96: Gant | I96: 1 | K96: 520 | L96: 4 | T96: Grand Total | U96: 991 | Z96: 78398.69 | AA96: 1 | AL96: 10643.38 | AM96: 1
B97: 64 | C97: 1 | E97: 15584766 | F97: 1 | H97: Gerasimov | I97: 1 | K97: 521 | L97: 2 | Z97: 78653.84 | AA97: 1 | AL97: 10656.89 | AM97: 1
B98: 65 | C98: 1 | E98: 15585036 | F98: 1 | H98: Ginikanwa | I98: 1 | K98: 522 | L98: 1 | Z98: 78707.16 | AA98: 1 | AL98: 10940.4 | AM98: 1
B99: 66 | C99: 1 | E99: 15585215 | F99: 1 | H99: Glauert | I99: 1 | K99: 523 | L99: 3 | Z99: 78992.75 | AA99: 1 | AL99: 11199.04 | AM99: 1
B100: 67 | C100: 1 | E100: 15585255 | F100: 1 | H100: Goforth | I100: 1 | K100: 524 | L100: 3 | Z100: 79019.8 | AA100: 1 | AL100: 11384.45 | AM100: 1
B101: 68 | C101: 1 | E101: 15585362 | F101: 1 | H101: Golovanov | I101: 1 | K101: 525 | L101: 4 | Z101: 79731.91 | AA101: 1 | AL101: 11723.57 | AM101: 1
B102: 69 | C102: 1 | E102: 15585388 | F102: 1 | H102: Graham | I102: 2 | K102: 526 | L102: 1 | Z102: 79871.02 | AA102: 1 | AL102: 12120.79 | AM102: 1
B103: 70 | C103: 1 | E103: 15585595 | F103: 1 | H103: Greeves | I103: 1 | K103: 527 | L103: 1 | Z103: 80001.23 | AA103: 1 | AL103: 12182.15 | AM103: 1
B104: 71 | C104: 1 | E104: 15585768 | F104: 1 | H104: Groves | I104: 1 | K104: 528 | L104: 2 | Z104: 80262.6 | AA104: 1 | AL104: 12796.43 | AM104: 1
B105: 72 | C105: 1 | E105: 15585865 | F105: 1 | H105: H? | I105: 1 | K105: 529 | L105: 2 | Z105: 80613.93 | AA105: 1 | AL105: 13107.24 | AM105: 1
B106: 73 | C106: 1 | E106: 15585888 | F106: 1 | H106: Hackett | I106: 1 | K106: 531 | L106: 4 | Z106: 80793.58 | AA106: 1 | AL106: 13601.79 | AM106: 1
B107: 74 | C107: 1 | E107: 15586310 | F107: 1 | H107: Hammond | I107: 1 | K107: 533 | L107: 1 | Z107: 81173.83 | AA107: 1 | AL107: 13898.31 | AM107: 1
B108: 75 | C108: 1 | E108: 15586585 | F108: 1 | H108: Hao | I108: 1 | K108: 534 | L108: 1 | Z108: 81273.13 | AA108: 1 | AL108: 14109.85 | AM108: 1
... B228: 195 | C228: 1 | E228: 15614782 | F228: 1 | H228: Grand Total | I228: 210 | K228: 661 | L228: 6 | Z228: 106138.33 | AA228: 1 | AL228: 38131.77 | AM228: 1
B229: 196 | C229: 1 | E229: 15615457 | F229: 1 | K229: 662 | L229: 2 | Z229: 106190.55 | AA229: 1 | AL229: 38152.01 | AM229: 1
B230: 197 | C230: 1 | E230: 15615624 | F230: 1 | K230: 663 | L230: 4 | Z230: 106192.1 | AA230: 1 | AL230: 38296.21 | AM230: 1
B231: 198 | C231: 1 | E231: 15616550 | F231: 1 | K231: 664 | L231: 5 | Z231: 106234.02 | AA231: 1 | AL231: 38411.79 | AM231: 1
B232: 199 | C232: 1 | E232: 15619304 | F232: 1 | K232: 665 | L232: 3 | Z232: 106307.91 | AA232: 1 | AL232: 38433.35 | AM232: 1
B233: 200 | C233: 1 | E233: 15619360 | F233: 1 | K233: 666 | L233: 1 | Z233: 106376.85 | AA233: 1 | AL233: 38812.67 | AM233: 1
B234: 201 | C234: 1 | E234: 15619529 | F234: 1 | K234: 667 | L234: 7 | Z234: 106518.52 | AA234: 1 | AL234: 38867.46 | AM234: 1
B235: 202 | C235: 1 | E235: 15619708 | F235: 1 | K235: 668 | L235: 6 | Z235: 106545.53 | AA235: 1 | AL235: 38913.68 | AM235: 1
B236: 203 | C236: 1 | E236: 15619857 | F236: 1 | K236: 669 | L236: 3 | Z236: 106854.21 | AA236: 1 | AL236: 38970.14 | AM236: 1
B237: 204 | C237: 1 | E237: 15619955 | F237: 1 | K237: 670 | L237: 3 | Z237: 106901.94 | AA237: 1 | AL237: 39087.42 | AM237: 1
B238: 205 | C238: 1 | E238: 15620204 | F238: 1 | K238: 671 | L238: 5 | Z238: 106937.05 | AA238: 1 | AL238: 39768.59 | AM238: 1
B239: 206 | C239: 1 | E239: 15620344 | F239: 1 | K239: 672 | L239: 2 | Z239: 106967.18 | AA239: 1 | AL239: 40014.76 | AM239: 1
B240: 207 | C240: 1 | E240: 15620505 | F240: 1 | K240: 673 | L240: 6 | Z240: 107042.74 | AA240: 1 | AL240: 40084.32 | AM240: 1
... B387: 354 | C387: 1 | E387: 15658935 | F387: 1 | K387: 850 | L387: 19 | Z387: 124695.72 | AA387: 1 | AL387: 72814.31 | AM387: 1
B388: 355 | C388: 1 | E388: 15659098 | F388: 1 | K388: (blank) | Z388: 124828.46 | AA388: 1 | AL388: 72924.56 | AM388: 1
B389: 356 | C389: 1 | E389: 15659366 | F389: 1 | K389: Grand Total | L389: 988 | Z389: 125013.72 | AA389: 1 | AL389: 73275.96 | AM389: 1
B390: 357 | C390: 1 | E390: 15659420 | F390: 1 | Z390: 125167.02 | AA390: 1 | AL390: 73294.48 | AM390: 1
B391: 358 | C391: 1 | E391: 15659428 | F391: 1 | Z391: 125169.26 | AA391: 1 | AL391: 73418.29 | AM391: 1
B392: 359 | C392: 1 | E392: 15659843 | F392: 1 | Z392: 125189.75 | AA392: 1 | AL392: 73564.44 | AM392: 1
B393: 360 | C393: 1 | E393: 15660101 | F393: 1 | Z393: 125211.92 | AA393: 1 | AL393: 73656.38 | AM393: 1
B394: 361 | C394: 1 | E394: 15660155 | F394: 1 | Z394: 125406.58 | AA394: 1 | AL394: 74077.91 | AM394: 1
B395: 362 | C395: 1 | E395: 15660211 | F395: 1 | Z395: 125510.82 | AA395: 1 | AL395: 74135.48 | AM395: 1
B396: 363 | C396: 1 | E396: 15660271 | F396: 1 | Z396: 125561.97 | AA396: 1 | AL396: 74158.8 | AM396: 1
B397: 364 | C397: 1 | E397: 15660429 | F397: 1 | Z397: 125832.2 | AA397: 1 | AL397: 74169.13 | AM397: 1
B398: 365 | C398: 1 | E398: 15660535 | F398: 1 | Z398: 125851.93 | AA398: 1 | AL398: 74835.65 | AM398: 1
B399: 366 | C399: 1 | E399: 15660602 | F399: 1 | Z399: 125884.95 | AA399: 1 | AL399: 74836.34 | AM399: 1
B400: 367 | C400: 1 | E400: 15661036 | F400: 1 | Z400: 126384.42 | AA400: 1 | AL400: 74890.58 | AM400: 1
B401: 368 | C401: 1 | E401: 15661249 | F401: 1 | Z401: 126418.14 | AA401: 1 | AL401: 74940.5 | AM401: 1
... B676: 643 | C676: 1 | E676: 15727556 | F676: 1 | Z676: 213146.2 | AA676: 1 | AL676: 126213.84 | AM676: 1
B677: 644 | C677: 1 | E677: 15727688 | F677: 1 | Z677: Grand Total | AA677: 991 | AL677: 126355.8 | AM677: 1
B678: 645 | C678: 1 | E678: 15727829 | F678: 1 | AL678: 126471.13 | AM678: 1
B679: 646 | C679: 1 | E679: 15727868 | F679: 1 | AL679: 126494.82 | AM679: 1
B680: 647 | C680: 1 | E680: 15727915 | F680: 1 | AL680: 126517.46 | AM680: 1
B681: 648 | C681: 1 | E681: 15728505 | F681: 1 | AL681: 126644.98 | AM681: 1
B682: 649 | C682: 1 | E682: 15728669 | F682: 1 | AL682: 126952.5 | AM682: 1
B683: 650 | C683: 1 | E683: 15728693 | F683: 1 | AL683: 127059.04 | AM683: 1
...

Sheet 04 - Data Quality
B2: Consistency
B4: Variables | C4: Problem | D4: Chosen method to solve | E4: Notes
B5: Gender | C5: Name varieties | D5: F changed to Female (19 cells updated) M changed to Male (49 cells updated) | E5: -
B6: Country | C6: Name varieties | D6: FR changed to France (244 cells updated) ES changed to Spain (118 cells updated) DE changed to Germany (23 cells updated) | E6: -
B7: Age | C7: There are 11 entries for an age of 2, which it is outside the age range of the given data and seems out of place | D7: The age of 2 should likely be 20 instead (an educated guess), as the age range from Spain goes from 20 to 75. The age of 2 changed to 20 (11 cells updated) | E7: These entries belong to Spain.
B10: Completeness
B12: Variables | C12: Problem | D12: Chosen method to solve | E12: Notes
B13: Estimated Salary | C13: There is 1 empty cell and 1 NULL cell | D13: The NULL cell: I filtered by country, gender, and age to find out the average estimated salary to assign. Changed to $113,951.12 (1 cell updated). The BLANK cell: I filtered by country, gender, and age to find out the average estimated salary to assign. Changed to $63,968.09 (1 cell updated) | E13: NULL: - Country = Germany, Gender = Male, Age = 26 - Customer ID #15785542 - Estimated salary average = $113,951.12 BLANK: - Country = Spain, Gender = Female, Age = 32 - Customer ID #15597945 - Estimated salary average = $63,968.09
B14: Balance | C14: There are 349 entries with $0 balance | D14: Do nothing - leave as is
B15: Last_Name | C15: There is 1 empty cell Other entries has a letter followed by ? | D15: The empty cell: Since this customer ID information is available, it is recommended to go to the source of the data to retrieve this customer's last name. Here, I would give it a name since I have no access to source data. If source data is available, I would go back and retrieve this customer's last name. The empty cell is filled with an alias name (Customer ID #15752047) "Not Given" | E15: This variable might not be necessary. Other entries where (?) is found might be corrupted.
B16: Credit Score | C16: There are 3 empty cells | D16: The credit score #1 is for (customer ID #15570060). The credit score #2 is for (customer ID #15785542). The credit score #3 is for (customer ID #15627801). I filtered by country, gender, and age to find out the average credit score to assign. #1: NULL changed to 663 (1 cell updated) #2: NULL changed to 697 (1 cell updated) #3: NULL changed to 680 (1 cell updated) | E16: #1: - Country = France, Gender = Female, Age = 43 - Credit score average = 663 #2: - Country = Germany, Gender = Male, Age = 26 - Credit score average = 697 #3: - Country = Spain, Gender = Male, Age = 33 - Credit score average = 680
B17: Gender | C17: There is 1 NULL cell | D17: The gender of (customer ID #15737173). I filtered by country and gender to find out the frequency of the values to assign the most frequent value to the NULL. NULL changed to Male (1 cell updated) | E17: - Country = Spain, Gender = Male - even without filtering by country, the most frequent gender is Male - Gender = Male
B18: Age | C18: There is 1 NULL cell | D18: The NULL for age (customer ID #15699309): Since the NULL is for a female from Spain, I filtered by female and Spain and found the average age to assign to the NULL. This age is the average age for females from Spain. The Null for Age changed to 38.
B20: Duplicates
B22: No duplicated rows found.

Sheet 05 - Cleaned data
A1: row_number | B1: customer_id | C1: last_name | D1: credit_score | E1: country | F1: gender | G1: age | H1: tenure | I1: balance | J1: num_of_products | K1: has_credit_card | L1: is_active_member | M1: estimated_salary | N1: exited_from_bank
A2: 1 | B2: 15634602 | C2: Hargrave | D2: 619 | E2: France | F2: Female | G2: 42 | H2: 2 | I2: 0 | J2: 1 | K2: 1 | L2: 1 | M2: 101348.88 | N2: 1
A3: 2 | B3: 15647311 | C3: Hill | D3: 608 | E3: Spain | F3: Female | G3: 41 | H3: 1 | I3: 83807.86 | J3: 1 | K3: 0 | L3: 1 | M3: 112542.58 | N3: 0
A4: 3 | B4: 15619304 | C4: Onio | D4: 502 | E4: France | F4: Female | G4: 42 | H4: 8 | I4: 159660.8 | J4: 3 | K4: 1 | L4: 0 | M4: 113931.57 | N4: 1
A5: 4 | B5: 15701354 | C5: Boni | D5: 699 | E5: France | F5: Female | G5: 39 | H5: 1 | I5: 0 | J5: 2 | K5: 0 | L5: 0 | M5: 93826.63 | N5: 0
A6: 5 | B6: 15737888 | C6: Mitchell | D6: 850 | E6: Spain | F6: Female | G6: 43 | H6: 2 | I6: 125510.82 | J6: 1 | K6: 1 | L6: 1 | M6: 79084.1 | N6: 0
A7: 6 | B7: 15574012 | C7: Chu | D7: 645 | E7: Spain | F7: Male | G7: 44 | H7: 8 | I7: 113755.78 | J7: 2 | K7: 1 | L7: 0 | M7: 149756.71 | N7: 1
A8: 7 | B8: 15592531 | C8: Bartlett | D8: 822 | E8: France | F8: Male | G8: 50 | H8: 7 | I8: 0 | J8: 2 | K8: 1 | L8: 1 | M8: 10062.8 | N8: 0
A9: 8 | B9: 15656148 | C9: Obinna | D9: 376 | E9: Germany | F9: Female | G9: 29 | H9: 4 | I9: 115046.74 | J9: 4 | K9: 1 | L9: 0 | M9: 119346.88 | N9: 1
A10: 9 | B10: 15792365 | C10: He | D10: 501 | E10: France | F10: Male | G10: 44 | H10: 4 | I10: 142051.07 | J10: 2 | K10: 0 | L10: 1 | M10: 74940.5 | N10: 0
A11: 10 | B11: 15592389 | C11: Xmissing | D11: 684 | E11: France | F11: Male | G11: 27 | H11: 2 | I11: 134603.88 | J11: 1 | K11: 1 | L11: 1 | M11: 71725.73 | N11: 0
A12: 11 | B12: 15767821 | C12: Bearce | D12: 528 | E12: France | F12: Male | G12: 31 | H12: 6 | I12: 102016.72 | J12: 2 | K12: 0 | L12: 0 | M12: 80181.12 | N12: 0
A13: 12 | B13: 15737173 | C13: Andrews | D13: 497 | E13: Spain | F13: Male | G13: 24 | H13: 3 | I13: 0 | J13: 2 | K13: 1 | L13: 0 | M13: 76390.01 | N13: 0
... A992: 991 | B992: 15745527 | C992: Burke | D992: 655 | E992: France | F992: Male | G992: 37 | H992: 5 | I992: 93147 | J992: 2 | K992: 1 | L992: 0 | M992: 66214.13 | N992: 0

Sheet 06 - Data Profiling_Cleaned
B2: Data Renaming/Reformatting
B4: Variables | C4: Changes
B5: last_name | C5: Customer_ID: 15592389; last_name: H? Customer_ID: 15624528; last_name: L? Customer_ID: 15624623; last_name: Hs? Customer_ID: 15805955; last_name: L? Customer_ID: 15582616; last_name: Y?an Customer_ID: 15676521; last_name: Y?an The question marks (?) indicate encoding problems or data corruption. The best approach would be to try to retrieve the data from the source with the correct encoding. As that's not possible, I will mark them as missing "Xmissing".
B6: Entire dataset | C6: Changed column names to lowercase and separated by _ for naming consistency
B8: Summary
B10: 14 variables, 991 records.
B14: Variables and Data Types
C17: Data Types
B18: Variables | C18: Time-variant/-invariant | D18: Structured/Unstructured | E18: Qualitative/Quantitative | F18: Qualitative: Nominal/Ordinal Quantitative: Discrete/Continuous
B19: row_number | C19: Time-invariant | D19: Structured | E19: Qualitative | F19: Nominal
B20: customer_id | C20: Time-invariant | D20: Structured | E20: Qualitative | F20: Nominal
B21: last_name | C21: Time-invariant | D21: Structured | E21: Qualitative | F21: Nominal
B22: credit_score | C22: Time-invariant | D22: Structured | E22: Quantitative | F22: Discrete
B23: country | C23: Time-invariant | D23: Structured | E23: Qualitative | F23: Nominal
B24: gender | C24: Time-invariant | D24: Structured | E24: Qualitative | F24: Nominal
B25: age | C25: Time-invariant | D25: Structured | E25: Quantitative | F25: Discrete | G25: Time-invariant (snapshot), but naturally time-variant
B26: tenure | C26: Time-invariant | D26: Structured | E26: Quantitative | F26: Discrete
B27: balance | C27: Time-variant | D27: Structured | E27: Quantitative | F27: Continuous
B28: num_of_products | C28: Time-variant | D28: Structured | E28: Quantitative | F28: Discrete
B29: has_credit_card | C29: Time-invariant | D29: Structured | E29: Qualitative | F29: Binary
B30: is_active_member | C30: Time-variant | D30: Structured | E30: Qualitative | F30: Binary
B31: estimated_salary | C31: Time-invariant | D31: Structured | E31: Quantitative | F31: Continuous
B32: exited_from_bank | C32: Time-invariant | D32: Structured | E32: Qualitative | F32: Binary

Sheet 07 - Data Integrity_Cleaned
B2: Data Accuracy
B4: (Numeric Columns) | C4: Minimum | D4: Maximum | E4: Mean
B5: credit_score | C5: =MIN('05 - Cleaned data'!D2:D992) -> 376 | D5: =MAX('05 - Cleaned data'!D2:D992) -> 850 | E5: =AVERAGE('05 - Cleaned data'!D2:D992) -> 648.60747
B6: age | C6: =MIN('05 - Cleaned data'!G2:G992) -> 18 | D6: =MAX('05 - Cleaned data'!G2:G992) -> 82 | E6: =AVERAGE('05 - Cleaned data'!G2:G992) -> 38.883956
B7: tenure | C7: =MIN('05 - Cleaned data'!H2:H992) -> 0 | D7: =MAX('05 - Cleaned data'!H2:H992) -> 10 | E7: =AVERAGE('05 - Cleaned data'!H2:H992) -> 5.0665994
B8: balance | C8: =MIN('05 - Cleaned data'!I2:I992) -> 0 | D8: =MAX('05 - Cleaned data'!I2:I992) -> 213146.2 | E8: =AVERAGE('05 - Cleaned data'!I2:I992) -> 78002.718
B9: num_of_products | C9: =MIN('05 - Cleaned data'!J2:J992) -> 1 | D9: =MAX('05 - Cleaned data'!J2:J992) -> 4 | E9: =AVERAGE('05 - Cleaned data'!J2:J992) -> 1.5227043
B10: estimated_salary | C10: =MIN('05 - Cleaned data'!M2:M992) -> 371.05 | D10: =MAX('05 - Cleaned data'!M2:M992) -> 199725.39 | E10: =AVERAGE('05 - Cleaned data'!M2:M992) -> 98555.138
B13: Data Consistency
B15: Variables | C15: Count | D15: Notes
B16: row_number | C16: 991 | D16: The dataset is now structurally sound.
B17: customer_id | C17: 991
B18: last_name | C18: 991
B19: credit_score | C19: 991
B20: country | C20: 991
B21: gender | C21: 991
B22: age | C22: 991
B23: tenure | C23: 991
B24: balance | C24: 991
B25: num_of_products | C25: 991
B26: has_credit_card | C26: 991
B27: is_active_member | C27: 991
B28: estimated_salary | C28: 991
B29: exited_from_bank | C29: 991
B31: (Frequency Tables)
B33: Row Labels | C33: Count of row_number | E33: Row Labels | F33: Count of customer_id | H33: Row Labels | I33: Count of last_name | K33: Row Labels | L33: Count of credit_score | N33: Row Labels | O33: Count of country | Q33: Row Labels | R33: Count of gender | T33: Row Labels | U33: Count of age | W33: Row Labels | X33: Count of tenure | Z33: Row Labels | AA33: Count of balance | AC33: Row Labels | AD33: Count of num_of_products | AF33: Row Labels | AG33: Count of has_credit_card | AI33: Row Labels | AJ33: Count of is_active_member | AL33: Row Labels | AM33: Count of estimated_salary | AO33: Row Labels | AP33: Count of exited_from_bank
B34: 1 | C34: 1 | E34: 15566091 | F34: 1 | H34: May | I34: 1 | K34: 376 | L34: 2 | N34: France | O34: 480 | Q34: Female | R34: 462 | T34: 18 | U34: 1 | W34: 0 | X34: 38 | Z34: 0 | AA34: 349 | AC34: 1 | AD34: 510 | AF34: 0 | AG34: 291 | AI34: 0 | AJ34: 488 | AL34: 371.05 | AM34: 1 | AO34: 0 | AP34: 787
B35: 2 | C35: 1 | E35: 15566111 | F35: 1 | H35: Sun | I35: 2 | K35: 411 | L35: 1 | N35: Germany | O35: 257 | Q35: Male | R35: 529 | T35: 19 | U35: 2 | W35: 1 | X35: 103 | Z35: 34013.63 | AA35: 1 | AC35: 2 | AD35: 446 | AF35: 1 | AG35: 700 | AI35: 1 | AJ35: 503 | AL35: 417.41 | AM35: 1 | AO35: 1 | AP35: 204
B36: 3 | C36: 1 | E36: 15566156 | F36: 1 | H36: Abbie | I36: 1 | K36: 413 | L36: 1 | N36: Spain | O36: 254 | Q36: Grand Total | R36: 991 | T36: 20 | U36: 12 | W36: 2 | X36: 110 | Z36: 37266.67 | AA36: 1 | AC36: 3 | AD36: 33 | AF36: Grand Total | AG36: 991 | AI36: Grand Total | AJ36: 991 | AL36: 447.73 | AM36: 1 | AO36: Grand Total | AP36: 991
B37: 4 | C37: 1 | E37: 15566292 | F37: 1 | H37: Achebe | I37: 1 | K37: 416 | L37: 2 | N37: Grand Total | O37: 991 | T37: 21 | U37: 6 | W37: 3 | X37: 101 | Z37: 40105.51 | AA37: 1 | AC37: 4 | AD37: 2 | AL37: 600.36 | AM37: 1
B38: 5 | C38: 1 | E38: 15566594 | F38: 1 | H38: Ahmed | I38: 1 | K38: 417 | L38: 1 | T38: 22 | U38: 7 | W38: 4 | X38: 86 | Z38: 40685.92 | AA38: 1 | AC38: Grand Total | AD38: 991 | AL38: 705.18 | AM38: 1
B39: 6 | C39: 1 | E39: 15567367 | F39: 1 | H39: Akeroyd | I39: 1 | K39: 421 | L39: 1 | T39: 23 | U39: 4 | W39: 5 | X39: 100 | Z39: 40915.55 | AA39: 1 | AL39: 777.37 | AM39: 1
B40: 7 | C40: 1 | E40: 15567446 | F40: 1 | H40: Alderete | I40: 1 | K40: 427 | L40: 1 | T40: 24 | U40: 15 | W40: 6 | X40: 94 | Z40: 42157.08 | AA40: 1 | AL40: 823.36 | AM40: 1
B41: 8 | C41: 1 | E41: 15567832 | F41: 1 | H41: Alekseeva | I41: 1 | K41: 429 | L41: 1 | T41: 25 | U41: 22 | W41: 7 | X41: 93 | Z41: 45144.43 | AA41: 1 | AL41: 878.87 | AM41: 1
B42: 9 | C42: 1 | E42: 15568240 | F42: 1 | H42: Aleshire | I42: 1 | K42: 432 | L42: 1 | T42: 26 | U42: 22 | W42: 8 | X42: 108 | Z42: 47134.75 | AA42: 1 | AL42: 1002.39 | AM42: 1
B43: 10 | C43: 1 | E43: 15568506 | F43: 1 | H43: Alexander | I43: 1 | K43: 435 | L43: 2 | T43: 27 | U43: 16 | W43: 9 | X43: 108 | Z43: 49512.55 | AA43: 1 | AL43: 1299.75 | AM43: 1
B44: 11 | C44: 1 | E44: 15568595 | F44: 1 | H44: Alexandrova | I44: 1 | K44: 438 | L44: 3 | T44: 28 | U44: 21 | W44: 10 | X44: 50 | Z44: 52436.2 | AA44: 1 | AL44: 1643.11 | AM44: 1
B45: 12 | C45: 1 | E45: 15568748 | F45: 1 | H45: Alexeeva | I45: 1 | K45: 439 | L45: 1 | T45: 29 | U45: 32 | W45: Grand Total | X45: 991 | Z45: 54503.55 | AA45: 1 | AL45: 1907.66 | AM45: 1
B46: 13 | C46: 1 | E46: 15568982 | F46: 1 | H46: Allard | I46: 1 | K46: 443 | L46: 2 | T46: 30 | U46: 32 | Z46: 54901.01 | AA46: 1 | AL46: 2010.98 | AM46: 1
B47: 14 | C47: 1 | E47: 15569590 | F47: 1 | H47: Allen | I47: 1 | K47: 445 | L47: 1 | T47: 31 | U47: 43 | Z47: 56084.69 | AA47: 1 | AL47: 2079.2 | AM47: 1
B48: 15 | C48: 1 | E48: 15569807 | F48: 1 | H48: Alley | I48: 1 | K48: 450 | L48: 1 | T48: 32 | U48: 37 | Z48: 56214.85 | AA48: 1 | AL48: 2319.96 | AM48: 1
B49: 16 | C49: 1 | E49: 15570060 | F49: 1 | H49: Amos | I49: 1 | K49: 456 | L49: 1 | T49: 33 | U49: 34 | Z49: 57017.06 | AA49: 1 | AL49: 2383.59 | AM49: 1
B50: 17 | C50: 1 | E50: 15570134 | F50: 1 | H50: Anderson | I50: 2 | K50: 459 | L50: 2 | T50: 34 | U50: 46 | Z50: 57929.81 | AA50: 1 | AL50: 3710.34 | AM50: 1
B51: 18 | C51: 1 | E51: 15571002 | F51: 1 | H51: Andrews | I51: 2 | K51: 460 | L51: 2 | T51: 35 | U51: 55 | Z51: 58469.37 | AA51: 1 | AL51: 3937.37 | AM51: 1
B52: 19 | C52: 1 | E52: 15571221 | F52: 1 | H52: Anenechi | I52: 1 | K52: 461 | L52: 1 | T52: 36 | U52: 59 | Z52: 58629.97 | AA52: 1 | AL52: 4389.4 | AM52: 1
B53: 20 | C53: 1 | E53: 15571816 | F53: 1 | H53: Angelo | I53: 1 | K53: 464 | L53: 2 | T53: 37 | U53: 45 | Z53: 58641.43 | AA53: 1 | AL53: 4400.32 | AM53: 1
B54: 21 | C54: 1 | E54: 15571928 | F54: 1 | H54: Ankudinov | I54: 1 | K54: 465 | L54: 1 | T54: 38 | U54: 43 | Z54: 59408.63 | AA54: 1 | AL54: 4861.72 | AM54: 1
B55: 22 | C55: 1 | E55: 15571973 | F55: 1 | H55: Archer | I55: 1 | K55: 468 | L55: 3 | T55: 39 | U55: 41 | Z55: 59697.17 | AA55: 1 | AL55: 5097.67 | AM55: 1
B56: 23 | C56: 1 | E56: 15572265 | F56: 1 | H56: Armstrong | I56: 1 | K56: 472 | L56: 1 | T56: 40 | U56: 32 | Z56: 61710.44 | AA56: 1 | AL56: 5472.7 | AM56: 1
B57: 24 | C57: 1 | E57: 15573112 | F57: 1 | H57: Artemiev | I57: 1 | K57: 474 | L57: 2 | T57: 41 | U57: 37 | Z57: 61825.5 | AA57: 1 | AL57: 5597.94 | AM57: 1
... B93: 60 | C93: 1 | E93: 15583456 | F93: 1 | H93: Benson | I93: 1 | K93: 517 | L93: 1 | T93: 82 | U93: 1 | Z93: 77637.35 | AA93: 1 | AL93: 10488.44 | AM93: 1
B94: 61 | C94: 1 | E94: 15583725 | F94: 1 | H94: Bergamaschi | I94: 1 | K94: 518 | L94: 1 | T94: Grand Total | U94: 991 | Z94: 77780.29 | AA94: 1 | AL94: 10553.31 | AM94: 1
B95: 62 | C95: 1 | E95: 15584091 | F95: 1 | H95: Bevington | I95: 1 | K95: 519 | L95: 3 | Z95: 77846.9 | AA95: 1 | AL95: 10598.29 | AM95: 1
B96: 63 | C96: 1 | E96: 15584518 | F96: 1 | H96: Bianchi | I96: 3 | K96: 520 | L96: 4 | Z96: 78398.69 | AA96: 1 | AL96: 10643.38 | AM96: 1
B97: 64 | C97: 1 | E97: 15584766 | F97: 1 | H97: Billson | I97: 1 | K97: 521 | L97: 2 | Z97: 78653.84 | AA97: 1 | AL97: 10656.89 | AM97: 1
B98: 65 | C98: 1 | E98: 15585036 | F98: 1 | H98: Bird | I98: 1 | K98: 522 | L98: 1 | Z98: 78707.16 | AA98: 1 | AL98: 10940.4 | AM98: 1
B99: 66 | C99: 1 | E99: 15585215 | F99: 1 | H99: Black | I99: 2 | K99: 523 | L99: 3 | Z99: 78992.75 | AA99: 1 | AL99: 11199.04 | AM99: 1
B100: 67 | C100: 1 | E100: 15585255 | F100: 1 | H100: Blackburn | I100: 1 | K100: 524 | L100: 3 | Z100: 79019.8 | AA100: 1 | AL100: 11384.45 | AM100: 1
B101: 68 | C101: 1 | E101: 15585362 | F101: 1 | H101: Blair | I101: 1 | K101: 525 | L101: 4 | Z101: 79731.91 | AA101: 1 | AL101: 11723.57 | AM101: 1
B102: 69 | C102: 1 | E102: 15585388 | F102: 1 | H102: Blakey | I102: 1 | K102: 526 | L102: 1 | Z102: 79871.02 | AA102: 1 | AL102: 12120.79 | AM102: 1
B103: 70 | C103: 1 | E103: 15585595 | F103: 1 | H103: Bledsoe | I103: 1 | K103: 527 | L103: 1 | Z103: 80001.23 | AA103: 1 | AL103: 12182.15 | AM103: 1
B104: 71 | C104: 1 | E104: 15585768 | F104: 1 | H104: Bobrov | I104: 1 | K104: 528 | L104: 2 | Z104: 80262.6 | AA104: 1 | AL104: 12796.43 | AM104: 1
B105: 72 | C105: 1 | E105: 15585865 | F105: 1 | H105: Boni | I105: 1 | K105: 529 | L105: 2 | Z105: 80613.93 | AA105: 1 | AL105: 13107.24 | AM105: 1
B106: 73 | C106: 1 | E106: 15585888 | F106: 1 | H106: Booth | I106: 1 | K106: 531 | L106: 4 | Z106: 80793.58 | AA106: 1 | AL106: 13601.79 | AM106: 1
... B387: 354 | C387: 1 | E387: 15658935 | F387: 1 | H387: Kornilova | I387: 1 | K387: 850 | L387: 19 | Z387: 124695.72 | AA387: 1 | AL387: 72467.99 | AM387: 1
B388: 355 | C388: 1 | E388: 15659098 | F388: 1 | H388: Kryukova | I388: 2 | K388: Grand Total | L388: 991 | Z388: 124828.46 | AA388: 1 | AL388: 72814.31 | AM388: 1
B389: 356 | C389: 1 | E389: 15659366 | F389: 1 | H389: Ku | I389: 3 | Z389: 125013.72 | AA389: 1 | AL389: 72924.56 | AM389: 1
B390: 357 | C390: 1 | E390: 15659420 | F390: 1 | H390: Kung | I390: 2 | Z390: 125167.02 | AA390: 1 | AL390: 73275.96 | AM390: 1
B391: 358 | C391: 1 | E391: 15659428 | F391: 1 | H391: Kuo | I391: 1 | Z391: 125169.26 | AA391: 1 | AL391: 73294.48 | AM391: 1
B392: 359 | C392: 1 | E392: 15659843 | F392: 1 | H392: Kuznetsova | I392: 1 | Z392: 125189.75 | AA392: 1 | AL392: 73418.29 | AM392: 1
B393: 360 | C393: 1 | E393: 15660101 | F393: 1 | H393: Lamb | I393: 1 | Z393: 125211.92 | AA393: 1 | AL393: 73564.44 | AM393: 1
B394: 361 | C394: 1 | E394: 15660155 | F394: 1 | H394: Landry | I394: 1 | Z394: 125406.58 | AA394: 1 | AL394: 73656.38 | AM394: 1
B395: 362 | C395: 1 | E395: 15660211 | F395: 1 | H395: Larionova | I395: 1 | Z395: 125510.82 | AA395: 1 | AL395: 74077.91 | AM395: 1
B396: 363 | C396: 1 | E396: 15660271 | F396: 1 | H396: Lattimore | I396: 1 | Z396: 125561.97 | AA396: 1 | AL396: 74135.48 | AM396: 1
B397: 364 | C397: 1 | E397: 15660429 | F397: 1 | H397: Lavine | I397: 1 | Z397: 125832.2 | AA397: 1 | AL397: 74158.8 | AM397: 1
B398: 365 | C398: 1 | E398: 15660535 | F398: 1 | H398: Lawrence | I398: 1 | Z398: 125851.93 | AA398: 1 | AL398: 74169.13 | AM398: 1
B399: 366 | C399: 1 | E399: 15660602 | F399: 1 | H399: Lazarev | I399: 1 | Z399: 125884.95 | AA399: 1 | AL399: 74835.65 | AM399: 1
B400: 367 | C400: 1 | E400: 15661036 | F400: 1 | H400: Lazareva | I400: 1 | Z400: 126384.42 | AA400: 1 | AL400: 74836.34 | AM400: 1
... B676: 643 | C676: 1 | E676: 15727556 | F676: 1 | H676: Taverner | I676: 1 | Z676: 213146.2 | AA676: 1 | AL676: 125777.28 | AM676: 1
B677: 644 | C677: 1 | E677: 15727688 | F677: 1 | H677: Taylor | I677: 1 | Z677: Grand Total | AA677: 991 | AL677: 126143.23 | AM677: 1
B678: 645 | C678: 1 | E678: 15727829 | F678: 1 | H678: Templeman | I678: 1 | AL678: 126213.84 | AM678: 1
B679: 646 | C679: 1 | E679: 15727868 | F679: 1 | H679: Teng | I679: 1 | AL679: 126355.8 | AM679: 1
B680: 647 | C680: 1 | E680: 15727915 | F680: 1 | H680: Thomsen | I680: 1 | AL680: 126471.13 | AM680: 1
B681: 648 | C681: 1 | E681: 15728505 | F681: 1 | H681: Thorpe | I681: 1 | AL681: 126494.82 | AM681: 1
B682: 649 | C682: 1 | E682: 15728669 | F682: 1 | H682: Thurgood | I682: 1 | AL682: 126517.46 | AM682: 1
B683: 650 | C683: 1 | E683: 15728693 | F683: 1 | H683: Tien | I683: 3 | AL683: 126644.98 | AM683: 1
B684: 651 | C684: 1 | E684: 15729362 | F684: 1 | H684: Ting | I684: 2 | AL684: 126952.5 | AM684: 1
B685: 652 | C685: 1 | E685: 15729599 | F685: 1 | H685: Titus | I685: 1 | AL685: 127059.04 | AM685: 1
B686: 653 | C686: 1 | E686: 15730059 | F686: 1 | H686: Toscani | I686: 2 | AL686: 127166.49 | AM686: 1
B687: 654 | C687: 1 | E687: 15730076 | F687: 1 | H687: Toscano | I687: 1 | AL687: 127569.8 | AM687: 1
B688: 655 | C688: 1 | E688: 15730447 | F688: 1 | H688: Treacy | I688: 1 | AL688: 127587.22 | AM688: 1
B689: 656 | C689: 1 | E689: 15730460 | F689: 1 | H689: Trentini | I689: 1 | AL689: 127951.81 | AM689: 1
... B765: 732 | C765: 1 | E765: 15750141 | F765: 1 | H765: Grand Total | I765: 991 | AL765: 144680.18 | AM765: 1
B766: 733 | C766: 1 | E766: 15750181 | F766: 1 | AL766: 144995.33 | AM766: 1
B767: 734 | C767: 1 | E767: 15750658 | F767: 1 | AL767: 145111.37 | AM767: 1
B768: 735 | C768: 1 | E768: 15750803 | F768: 1 | AL768: 145251.35 | AM768: 1
B769: 736 | C769: 1 | E769: 15751208 | F769: 1 | AL769: 145562.4 | AM769: 1
B770: 737 | C770: 1 | E770: 15751710 | F770: 1 | AL770: 145593.85 | AM770: 1
B771: 738 | C771: 1 | E771: 15752047 | F771: 1 | AL771: 145700.22 | AM771: 1
B772: 739 | C772: 1 | E772: 15752081 | F772: 1 | AL772: 145704.19 | AM772: 1
...

Sheet 08 - Derived data
A1: row_number | B1: customer_id | C1: last_name | D1: credit_score | E1: country | F1: gender | G1: age | H1: tenure | I1: balance | J1: num_of_products | K1: has_credit_card | L1: is_active_member | M1: estimated_salary | N1: exited_from_bank | O1: credit_score_quality | P1: age_category | Q1: balance_category | R1: estimated_salary_range
A2: 1 | B2: 15634602 | C2: Hargrave | D2: 619 | E2: France | F2: Female | G2: 42 | H2: 2 | I2: 0 | J2: 1 | K2: 1 | L2: 1 | M2: 101348.88 | N2: 1 | O2: =IF(D2>=721, "Good", IF(D2>=521, "Fair", "Poor")) -> Fair | P2: =IF(G2>=60, "Senior adult", IF(G2>=40, "Middle-aged adult", "Young adult")) -> Middle-aged adult | Q2: =IF(I2>=126000, "High-Balance", IF(I2>=76000, "Mid-Balance", "Low-Balance")) -> Low-Balance | R2: =IF(M2>=151000,"151,000 - 200,00",IF(M2>=101000,"101,000 - 150,000",IF(M2>=51000,"51,000 - 100,000"," 0 - 50,000"))) -> 101,000 - 150,000
A3: 2 | B3: 15647311 | C3: Hill | D3: 608 | E3: Spain | F3: Female | G3: 41 | H3: 1 | I3: 83807.86 | J3: 1 | K3: 0 | L3: 1 | M3: 112542.58 | N3: 0 | O3: =IF(D3>=721, "Good", IF(D3>=521, "Fair", "Poor")) -> Fair | P3: =IF(G3>=60, "Senior adult", IF(G3>=40, "Middle-aged adult", "Young adult")) -> Middle-aged adult | Q3: =IF(I3>=126000, "High-Balance", IF(I3>=76000, "Mid-Balance", "Low-Balance")) -> Mid-Balance | R3: =IF(M3>=151000,"151,000 - 200,00",IF(M3>=101000,"101,000 - 150,000",IF(M3>=51000,"51,000 - 100,000"," 0 - 50,000"))) -> 101,000 - 150,000
A4: 3 | B4: 15619304 | C4: Onio | D4: 502 | E4: France | F4: Female | G4: 42 | H4: 8 | I4: 159660.8 | J4: 3 | K4: 1 | L4: 0 | M4: 113931.57 | N4: 1 | O4: =IF(D4>=721, "Good", IF(D4>=521, "Fair", "Poor")) -> Poor | P4: =IF(G4>=60, "Senior adult", IF(G4>=40, "Middle-aged adult", "Young adult")) -> Middle-aged adult | Q4: =IF(I4>=126000, "High-Balance", IF(I4>=76000, "Mid-Balance", "Low-Balance")) -> High-Balance | R4: =IF(M4>=151000,"151,000 - 200,00",IF(M4>=101000,"101,000 - 150,000",IF(M4>=51000,"51,000 - 100,000"," 0 - 50,000"))) -> 101,000 - 150,000
A5: 4 | B5: 15701354 | C5: Boni | D5: 699 | E5: France | F5: Female | G5: 39 | H5: 1 | I5: 0 | J5: 2 | K5: 0 | L5: 0 | M5: 93826.63 | N5: 0 | O5: =IF(D5>=721, "Good", IF(D5>=521, "Fair", "Poor")) -> Fair | P5: =IF(G5>=60, "Senior adult", IF(G5>=40, "Middle-aged adult", "Young adult")) -> Young adult | Q5: =IF(I5>=126000, "High-Balance", IF(I5>=76000, "Mid-Balance", "Low-Balance")) -> Low-Balance | R5: =IF(M5>=151000,"151,000 - 200,00",IF(M5>=101000,"101,000 - 150,000",IF(M5>=51000,"51,000 - 100,000"," 0 - 50,000"))) -> 51,000 - 100,000
A6: 5 | B6: 15737888 | C6: Mitchell | D6: 850 | E6: Spain | F6: Female | G6: 43 | H6: 2 | I6: 125510.82 | J6: 1 | K6: 1 | L6: 1 | M6: 79084.1 | N6: 0 | O6: =IF(D6>=721, "Good", IF(D6>=521, "Fair", "Poor")) -> Good | P6: =IF(G6>=60, "Senior adult", IF(G6>=40, "Middle-aged adult", "Young adult")) -> Middle-aged adult | Q6: =IF(I6>=126000, "High-Balance", IF(I6>=76000, "Mid-Balance", "Low-Balance")) -> Mid-Balance | R6: =IF(M6>=151000,"151,000 - 200,00",IF(M6>=101000,"101,000 - 150,000",IF(M6>=51000,"51,000 - 100,000"," 0 - 50,000"))) -> 51,000 - 100,000
A7: 6 | B7: 15574012 | C7: Chu | D7: 645 | E7: Spain | F7: Male | G7: 44 | H7: 8 | I7: 113755.78 | J7: 2 | K7: 1 | L7: 0 | M7: 149756.71 | N7: 1 | O7: =IF(D7>=721, "Good", IF(D7>=521, "Fair", "Poor")) -> Fair | P7: =IF(G7>=60, "Senior adult", IF(G7>=40, "Middle-aged adult", "Young adult")) -> Middle-aged adult | Q7: =IF(I7>=126000, "High-Balance", IF(I7>=76000, "Mid-Balance", "Low-Balance")) -> Mid-Balance | R7: =IF(M7>=151000,"151,000 - 200,00",IF(M7>=101000,"101,000 - 150,000",IF(M7>=51000,"51,000 - 100,000"," 0 - 50,000"))) -> 101,000 - 150,000
A8: 7 | B8: 15592531 | C8: Bartlett | D8: 822 | E8: France | F8: Male | G8: 50 | H8: 7 | I8: 0 | J8: 2 | K8: 1 | L8: 1 | M8: 10062.8 | N8: 0 | O8: =IF(D8>=721, "Good", IF(D8>=521, "Fair", "Poor")) -> Good | P8: =IF(G8>=60, "Senior adult", IF(G8>=40, "Middle-aged adult", "Young adult")) -> Middle-aged adult | Q8: =IF(I8>=126000, "High-Balance", IF(I8>=76000, "Mid-Balance", "Low-Balance")) -> Low-Balance | R8: =IF(M8>=151000,"151,000 - 200,00",IF(M8>=101000,"101,000 - 150,000",IF(M8>=51000,"51,000 - 100,000"," 0 - 50,000"))) -> 0 - 50,000
A9: 8 | B9: 15656148 | C9: Obinna | D9: 376 | E9: Germany | F9: Female | G9: 29 | H9: 4 | I9: 115046.74 | J9: 4 | K9: 1 | L9: 0 | M9: 119346.88 | N9: 1 | O9: =IF(D9>=721, "Good", IF(D9>=521, "Fair", "Poor")) -> Poor | P9: =IF(G9>=60, "Senior adult", IF(G9>=40, "Middle-aged adult", "Young adult")) -> Young adult | Q9: =IF(I9>=126000, "High-Balance", IF(I9>=76000, "Mid-Balance", "Low-Balance")) -> Mid-Balance | R9: =IF(M9>=151000,"151,000 - 200,00",IF(M9>=101000,"101,000 - 150,000",IF(M9>=51000,"51,000 - 100,000"," 0 - 50,000"))) -> 101,000 - 150,000
A10: 9 | B10: 15792365 | C10: He | D10: 501 | E10: France | F10: Male | G10: 44 | H10: 4 | I10: 142051.07 | J10: 2 | K10: 0 | L10: 1 | M10: 74940.5 | N10: 0 | O10: =IF(D10>=721, "Good", IF(D10>=521, "Fair", "Poor")) -> Poor | P10: =IF(G10>=60, "Senior adult", IF(G10>=40, "Middle-aged adult", "Young adult")) -> Middle-aged adult | Q10: =IF(I10>=126000, "High-Balance", IF(I10>=76000, "Mid-Balance", "Low-Balance")) -> High-Balance | R10: =IF(M10>=151000,"151,000 - 200,00",IF(M10>=101000,"101,000 - 150,000",IF(M10>=51000,"51,000 - 100,000"," 0 - 50,000"))) -> 51,000 - 100,000
A11: 10 | B11: 15592389 | C11: Xmissing | D11: 684 | E11: France | F11: Male | G11: 27 | H11: 2 | I11: 134603.88 | J11: 1 | K11: 1 | L11: 1 | M11: 71725.73 | N11: 0 | O11: =IF(D11>=721, "Good", IF(D11>=521, "Fair", "Poor")) -> Fair | P11: =IF(G11>=60, "Senior adult", IF(G11>=40, "Middle-aged adult", "Young adult")) -> Young adult | Q11: =IF(I11>=126000, "High-Balance", IF(I11>=76000, "Mid-Balance", "Low-Balance")) -> High-Balance | R11: =IF(M11>=151000,"151,000 - 200,00",IF(M11>=101000,"101,000 - 150,000",IF(M11>=51000,"51,000 - 100,000"," 0 - 50,000"))) -> 51,000 - 100,000
A12: 11 | B12: 15767821 | C12: Bearce | D12: 528 | E12: France | F12: Male | G12: 31 | H12: 6 | I12: 102016.72 | J12: 2 | K12: 0 | L12: 0 | M12: 80181.12 | N12: 0 | O12: =IF(D12>=721, "Good", IF(D12>=521, "Fair", "Poor")) -> Fair | P12: =IF(G12>=60, "Senior adult", IF(G12>=40, "Middle-aged adult", "Young adult")) -> Young adult | Q12: =IF(I12>=126000, "High-Balance", IF(I12>=76000, "Mid-Balance", "Low-Balance")) -> Mid-Balance | R12: =IF(M12>=151000,"151,000 - 200,00",IF(M12>=101000,"101,000 - 150,000",IF(M12>=51000,"51,000 - 100,000"," 0 - 50,000"))) -> 51,000 - 100,000
A13: 12 | B13: 15737173 | C13: Andrews | D13: 497 | E13: Spain | F13: Male | G13: 24 | H13: 3 | I13: 0 | J13: 2 | K13: 1 | L13: 0 | M13: 76390.01 | N13: 0 | O13: =IF(D13>=721, "Good", IF(D13>=521, "Fair", "Poor")) -> Poor | P13: =IF(G13>=60, "Senior adult", IF(G13>=40, "Middle-aged adult", "Young adult")) -> Young adult | Q13: =IF(I13>=126000, "High-Balance", IF(I13>=76000, "Mid-Balance", "Low-Balance")) -> Low-Balance | R13: =IF(M13>=151000,"151,000 - 200,00",IF(M13>=101000,"101,000 - 150,000",IF(M13>=51000,"51,000 - 100,000"," 0 - 50,000"))) -> 51,000 - 100,000
... A992: 991 | B992: 15745527 | C992: Burke | D992: 655 | E992: France | F992: Male | G992: 37 | H992: 5 | I992: 93147 | J992: 2 | K992: 1 | L992: 0 | M992: 66214.13 | N992: 0 | O992: =IF(D992>=721, "Good", IF(D992>=521, "Fair", "Poor")) -> Fair | P992: =IF(G992>=60, "Senior adult", IF(G992>=40, "Middle-aged adult", "Young adult")) -> Young adult | Q992: =IF(I992>=126000, "High-Balance", IF(I992>=76000, "Mid-Balance", "Low-Balance")) -> Mid-Balance | R992: =IF(M992>=151000,"151,000 - 200,00",IF(M992>=101000,"101,000 - 150,000",IF(M992>=51000,"51,000 - 100,000"," 0 - 50,000"))) -> 51,000 - 100,000

Sheet 09 - Customers stayed
A1: row_number | B1: customer_id | C1: last_name | D1: credit_score | E1: country | F1: gender | G1: age | H1: tenure | I1: balance | J1: num_of_products | K1: has_credit_card | L1: is_active_member | M1: estimated_salary | N1: exited_from_bank | O1: credit_score_quality | P1: age_category | Q1: balance_category | R1: estimated_salary_range
A2: 2 | B2: 15647311 | C2: Hill | D2: 608 | E2: Spain | F2: Female | G2: 41 | H2: 1 | I2: 83807.86 | J2: 1 | K2: 0 | L2: 1 | M2: 112542.58 | N2: 0 | O2: Fair | P2: Middle-aged adult | Q2: Mid-Balance | R2: 101,000 - 150,000
A3: 4 | B3: 15701354 | C3: Boni | D3: 699 | E3: France | F3: Female | G3: 39 | H3: 1 | I3: 0 | J3: 2 | K3: 0 | L3: 0 | M3: 93826.63 | N3: 0 | O3: Fair | P3: Young adult | Q3: Low-Balance | R3: 51,000 - 100,000
A4: 5 | B4: 15737888 | C4: Mitchell | D4: 850 | E4: Spain | F4: Female | G4: 43 | H4: 2 | I4: 125510.82 | J4: 1 | K4: 1 | L4: 1 | M4: 79084.1 | N4: 0 | O4: Good | P4: Middle-aged adult | Q4: Mid-Balance | R4: 51,000 - 100,000
A5: 7 | B5: 15592531 | C5: Bartlett | D5: 822 | E5: France | F5: Male | G5: 50 | H5: 7 | I5: 0 | J5: 2 | K5: 1 | L5: 1 | M5: 10062.8 | N5: 0 | O5: Good | P5: Middle-aged adult | Q5: Low-Balance | R5: 0 - 50,000
A6: 9 | B6: 15792365 | C6: He | D6: 501 | E6: France | F6: Male | G6: 44 | H6: 4 | I6: 142051.07 | J6: 2 | K6: 0 | L6: 1 | M6: 74940.5 | N6: 0 | O6: Poor | P6: Middle-aged adult | Q6: High-Balance | R6: 51,000 - 100,000
A7: 10 | B7: 15592389 | C7: Xmissing | D7: 684 | E7: France | F7: Male | G7: 27 | H7: 2 | I7: 134603.88 | J7: 1 | K7: 1 | L7: 1 | M7: 71725.73 | N7: 0 | O7: Fair | P7: Young adult | Q7: High-Balance | R7: 51,000 - 100,000
A8: 11 | B8: 15767821 | C8: Bearce | D8: 528 | E8: France | F8: Male | G8: 31 | H8: 6 | I8: 102016.72 | J8: 2 | K8: 0 | L8: 0 | M8: 80181.12 | N8: 0 | O8: Fair | P8: Young adult | Q8: Mid-Balance | R8: 51,000 - 100,000
A9: 12 | B9: 15737173 | C9: Andrews | D9: 497 | E9: Spain | F9: Male | G9: 24 | H9: 3 | I9: 0 | J9: 2 | K9: 1 | L9: 0 | M9: 76390.01 | N9: 0 | O9: Poor | P9: Young adult | Q9: Low-Balance | R9: 51,000 - 100,000
A10: 13 | B10: 15632264 | C10: Kay | D10: 476 | E10: France | F10: Female | G10: 34 | H10: 10 | I10: 0 | J10: 2 | K10: 1 | L10: 0 | M10: 26260.98 | N10: 0 | O10: Poor | P10: Young adult | Q10: Low-Balance | R10: 0 - 50,000
A11: 14 | B11: 15691483 | C11: Chin | D11: 549 | E11: France | F11: Female | G11: 25 | H11: 5 | I11: 0 | J11: 2 | K11: 0 | L11: 0 | M11: 190857.79 | N11: 0 | O11: Fair | P11: Young adult | Q11: Low-Balance | R11: 151,000 - 200,00
A12: 15 | B12: 15600882 | C12: Scott | D12: 635 | E12: Spain | F12: Female | G12: 35 | H12: 7 | I12: 0 | J12: 2 | K12: 1 | L12: 1 | M12: 65951.65 | N12: 0 | O12: Fair | P12: Young adult | Q12: Low-Balance | R12: 51,000 - 100,000
A13: 16 | B13: 15643966 | C13: Goforth | D13: 616 | E13: Germany | F13: Male | G13: 45 | H13: 3 | I13: 143129.41 | J13: 2 | K13: 0 | L13: 1 | M13: 64327.26 | N13: 0 | O13: Fair | P13: Middle-aged adult | Q13: High-Balance | R13: 51,000 - 100,000
... A788: 991 | B788: 15745527 | C788: Burke | D788: 655 | E788: France | F788: Male | G788: 37 | H788: 5 | I788: 93147 | J788: 2 | K788: 1 | L788: 0 | M788: 66214.13 | N788: 0 | O788: Fair | P788: Young adult | Q788: Mid-Balance | R788: 51,000 - 100,000

Sheet 10 - Customers left
A1: row_number | B1: customer_id | C1: last_name | D1: credit_score | E1: country | F1: gender | G1: age | H1: tenure | I1: balance | J1: num_of_products | K1: has_credit_card | L1: is_active_member | M1: estimated_salary | N1: exited_from_bank | O1: credit_score_quality | P1: age_category | Q1: balance_category | R1: estimated_salary_range
A2: 1 | B2: 15634602 | C2: Hargrave | D2: 619 | E2: France | F2: Female | G2: 42 | H2: 2 | I2: 0 | J2: 1 | K2: 1 | L2: 1 | M2: 101348.88 | N2: 1 | O2: Fair | P2: Middle-aged adult | Q2: Low-Balance | R2: 101,000 - 150,000
A3: 3 | B3: 15619304 | C3: Onio | D3: 502 | E3: France | F3: Female | G3: 42 | H3: 8 | I3: 159660.8 | J3: 3 | K3: 1 | L3: 0 | M3: 113931.57 | N3: 1 | O3: Poor | P3: Middle-aged adult | Q3: High-Balance | R3: 101,000 - 150,000
A4: 6 | B4: 15574012 | C4: Chu | D4: 645 | E4: Spain | F4: Male | G4: 44 | H4: 8 | I4: 113755.78 | J4: 2 | K4: 1 | L4: 0 | M4: 149756.71 | N4: 1 | O4: Fair | P4: Middle-aged adult | Q4: Mid-Balance | R4: 101,000 - 150,000
A5: 8 | B5: 15656148 | C5: Obinna | D5: 376 | E5: Germany | F5: Female | G5: 29 | H5: 4 | I5: 115046.74 | J5: 4 | K5: 1 | L5: 0 | M5: 119346.88 | N5: 1 | O5: Poor | P5: Young adult | Q5: Mid-Balance | R5: 101,000 - 150,000
A6: 17 | B6: 15737452 | C6: Romeo | D6: 653 | E6: Germany | F6: Male | G6: 58 | H6: 1 | I6: 132602.88 | J6: 1 | K6: 1 | L6: 0 | M6: 5097.67 | N6: 1 | O6: Fair | P6: Middle-aged adult | Q6: High-Balance | R6: 0 - 50,000
A7: 23 | B7: 15699309 | C7: Gerasimov | D7: 510 | E7: Spain | F7: Female | G7: 38 | H7: 4 | I7: 0 | J7: 1 | K7: 1 | L7: 0 | M7: 118913.53 | N7: 1 | O7: Poor | P7: Young adult | Q7: Low-Balance | R7: 101,000 - 150,000
A8: 31 | B8: 15589475 | C8: Azikiwe | D8: 591 | E8: Spain | F8: Female | G8: 39 | H8: 3 | I8: 0 | J8: 3 | K8: 1 | L8: 0 | M8: 140469.38 | N8: 1 | O8: Fair | P8: Young adult | Q8: Low-Balance | R8: 101,000 - 150,000
A9: 36 | B9: 15794171 | C9: Lombardo | D9: 475 | E9: France | F9: Female | G9: 45 | H9: 0 | I9: 134264.04 | J9: 1 | K9: 1 | L9: 0 | M9: 27822.99 | N9: 1 | O9: Poor | P9: Middle-aged adult | Q9: High-Balance | R9: 0 - 50,000
A10: 42 | B10: 15738148 | C10: Clarke | D10: 465 | E10: France | F10: Female | G10: 51 | H10: 8 | I10: 122522.32 | J10: 1 | K10: 0 | L10: 0 | M10: 181297.65 | N10: 1 | O10: Poor | P10: Middle-aged adult | Q10: Mid-Balance | R10: 151,000 - 200,00
A11: 44 | B11: 15755196 | C11: Lavine | D11: 834 | E11: France | F11: Female | G11: 49 | H11: 2 | I11: 131394.56 | J11: 1 | K11: 0 | L11: 0 | M11: 194365.76 | N11: 1 | O11: Good | P11: Middle-aged adult | Q11: High-Balance | R11: 151,000 - 200,00
A12: 47 | B12: 15602280 | C12: Martin | D12: 829 | E12: Germany | F12: Female | G12: 27 | H12: 9 | I12: 112045.67 | J12: 1 | K12: 1 | L12: 1 | M12: 119708.21 | N12: 1 | O12: Good | P12: Young adult | Q12: Mid-Balance | R12: 101,000 - 150,000
A13: 48 | B13: 15771573 | C13: Okagbue | D13: 637 | E13: Germany | F13: Female | G13: 39 | H13: 9 | I13: 137843.8 | J13: 1 | K13: 1 | L13: 1 | M13: 117622.8 | N13: 1 | O13: Fair | P13: Young adult | Q13: High-Balance | R13: 101,000 - 150,000
... A205: 990 | B205: 15681206 | C205: Hsing | D205: 722 | E205: France | F205: Female | G205: 49 | H205: 3 | I205: 168197.66 | J205: 1 | K205: 1 | L205: 0 | M205: 140765.57 | N205: 1 | O205: Good | P205: Middle-aged adult | Q205: High-Balance | R205: 101,000 - 150,000

Sheet 11 - Pivot tables
B2: Customers stayed
D4: Credit Score Quality | H4: Country | L4: Gender | P4: Age category
B5: Row Labels | C5: Count of credit_score_quality | D5: % | F5: Row Labels | G5: Count of country | H5: % | J5: Row Labels | K5: Count of gender | L5: % | N5: Row Labels | O5: Count of age_category | P5: %
B6: Fair | C6: 496 | D6: =GETPIVOTDATA("credit_score_quality",$B$5,"credit_score_quality","Fair")/GETPIVOTDATA("credit_score_quality",$B$5) -> 0.63024142 | F6: France | G6: 403 | H6: =+GETPIVOTDATA("country",$F$5,"country","France")/GETPIVOTDATA("country",$F$5) -> 0.51207116 | J6: Female | K6: 341 | L6: =+GETPIVOTDATA("gender",$J$5,"gender","Female")/GETPIVOTDATA("gender",$J$5) -> 0.43329098 | N6: Middle-aged adult | O6: 221 | P6: =+GETPIVOTDATA("age_category",$N$5,"age_category","Middle-aged adult")/GETPIVOTDATA("age_category",$N$5) -> 0.28081321
B7: Good | C7: 203 | D7: =+GETPIVOTDATA("credit_score_quality",$B$5,"credit_score_quality","Good")/GETPIVOTDATA("credit_score_quality",$B$5) -> 0.25794155 | F7: Germany | G7: 182 | H7: =+GETPIVOTDATA("country",$F$5,"country","Germany")/GETPIVOTDATA("country",$F$5) -> 0.23125794 | J7: Male | K7: 446 | L7: =+GETPIVOTDATA("gender",$J$5,"gender","Male")/GETPIVOTDATA("gender",$J$5) -> 0.56670902 | N7: Senior adult | O7: 31 | P7: =+GETPIVOTDATA("age_category",$N$5,"age_category","Senior adult")/GETPIVOTDATA("age_category",$N$5) -> 0.039390089
B8: Poor | C8: 88 | D8: =+GETPIVOTDATA("credit_score_quality",$B$5,"credit_score_quality","Poor")/GETPIVOTDATA("credit_score_quality",$B$5) -> 0.11181703 | F8: Spain | G8: 202 | H8: =+GETPIVOTDATA("country",$F$5,"country","Spain")/GETPIVOTDATA("country",$F$5) -> 0.2566709 | J8: Grand Total | K8: 787 | N8: Young adult | O8: 535 | P8: =+GETPIVOTDATA("age_category",$N$5,"age_category","Young adult")/GETPIVOTDATA("age_category",$N$5) -> 0.6797967
B9: Grand Total | C9: 787 | F9: Grand Total | G9: 787 | N9: Grand Total | O9: 787
D12: Tenure | H12: Balance category | L12: Number of products | P12: Has credit card?
B13: Row Labels | C13: Count of tenure | D13: % | F13: Row Labels | G13: Count of balance_category | H13: % | J13: Row Labels | K13: Count of num_of_products | L13: % | N13: Row Labels | O13: Count of has_credit_card | P13: %
B14: 0 | C14: 32 | D14: =+GETPIVOTDATA("tenure",$B$13,"tenure",0)/GETPIVOTDATA("tenure",$B$13) -> 0.040660737 | F14: High-Balance | G14: 207 | H14: =+GETPIVOTDATA("balance_category",$F$13,"balance_category","High-Balance")/GETPIVOTDATA("balance_category",$F$13) -> 0.26302414 | J14: 1 | K14: 368 | L14: =+GETPIVOTDATA("num_of_products",$J$13,"num_of_products",1)/GETPIVOTDATA("num_of_products",$J$13) -> 0.46759848 | N14: 0 | O14: 231 | P14: =+GETPIVOTDATA("has_credit_card",$N$13,"has_credit_card",0)/GETPIVOTDATA("has_credit_card",$N$13) -> 0.2935197
B15: 1 | C15: 73 | D15: =+GETPIVOTDATA("tenure",$B$13,"tenure",1)/GETPIVOTDATA("tenure",$B$13) -> 0.092757306 | F15: Low-Balance | G15: 335 | H15: =+GETPIVOTDATA("balance_category",$F$13,"balance_category","Low-Balance")/GETPIVOTDATA("balance_category",$F$13) -> 0.42566709 | J15: 2 | K15: 414 | L15: =+GETPIVOTDATA("num_of_products",$J$13,"num_of_products",2)/GETPIVOTDATA("num_of_products",$J$13) -> 0.52604828 | N15: 1 | O15: 556 | P15: =+GETPIVOTDATA("has_credit_card",$N$13,"has_credit_card",1)/GETPIVOTDATA("has_credit_card",$N$13) -> 0.7064803
B16: 2 | C16: 83 | D16: =+GETPIVOTDATA("tenure",$B$13,"tenure",2)/GETPIVOTDATA("tenure",$B$13) -> 0.10546379 | F16: Mid-Balance | G16: 245 | H16: =+GETPIVOTDATA("balance_category",$F$13,"balance_category","Mid-Balance")/GETPIVOTDATA("balance_category",$F$13) -> 0.31130877 | J16: 3 | K16: 5 | L16: =+GETPIVOTDATA("num_of_products",$J$13,"num_of_products",3)/GETPIVOTDATA("num_of_products",$J$13) -> 0.0063532402 | N16: Grand Total | O16: 787
B17: 3 | C17: 81 | D17: =+GETPIVOTDATA("tenure",$B$13,"tenure",3)/GETPIVOTDATA("tenure",$B$13) -> 0.10292249 | F17: Grand Total | G17: 787 | J17: Grand Total | K17: 787
B18: 4 | C18: 69 | D18: =+GETPIVOTDATA("tenure",$B$13,"tenure",4)/GETPIVOTDATA("tenure",$B$13) -> 0.087674714
B19: 5 | C19: 80 | D19: =+GETPIVOTDATA("tenure",$B$13,"tenure",5)/GETPIVOTDATA("tenure",$B$13) -> 0.10165184
B20: 6 | C20: 73 | D20: =+GETPIVOTDATA("tenure",$B$13,"tenure",6)/GETPIVOTDATA("tenure",$B$13) -> 0.092757306 | H20: Is active member? | L20: Estimated salary range
B21: 7 | C21: 78 | D21: =+GETPIVOTDATA("tenure",$B$13,"tenure",7)/GETPIVOTDATA("tenure",$B$13) -> 0.099110546 | F21: Row Labels | G21: Count of is_active_member | H21: % | J21: Row Labels | K21: Count of estimated_salary_range | L21: %
B22: 8 | C22: 88 | D22: =+GETPIVOTDATA("tenure",$B$13,"tenure",8)/GETPIVOTDATA("tenure",$B$13) -> 0.11181703 | F22: 0 | G22: 345 | H22: =+GETPIVOTDATA("is_active_member",$F$21,"is_active_member",0)/GETPIVOTDATA("is_active_member",$F$21) -> 0.43837357 | J22: 0 - 50,000 | K22: 196 | L22: =+GETPIVOTDATA("estimated_salary_range",$J$21,"estimated_salary_range"," 0 - 50,000")/GETPIVOTDATA("estimated_salary_range",$J$21) -> 0.24904701
B23: 9 | C23: 87 | D23: =+GETPIVOTDATA("tenure",$B$13,"tenure",9)/GETPIVOTDATA("tenure",$B$13) -> 0.11054638 | F23: 1 | G23: 442 | H23: =+GETPIVOTDATA("is_active_member",$F$21,"is_active_member",1)/GETPIVOTDATA("is_active_member",$F$21) -> 0.56162643 | J23: 101,000 - 150,000 | K23: 204 | L23: =+GETPIVOTDATA("estimated_salary_range",$J$21,"estimated_salary_range","101,000 - 150,000")/GETPIVOTDATA("estimated_salary_range",$J$21) -> 0.2592122
B24: 10 | C24: 43 | D24: =+GETPIVOTDATA("tenure",$B$13,"tenure",10)/GETPIVOTDATA("tenure",$B$13) -> 0.054637865 | F24: Grand Total | G24: 787 | J24: 151,000 - 200,00 | K24: 176 | L24: =+GETPIVOTDATA("estimated_salary_range",$J$21,"estimated_salary_range","151,000 - 200,00")/GETPIVOTDATA("estimated_salary_range",$J$21) -> 0.22363405
B25: Grand Total | C25: 787 | J25: 51,000 - 100,000 | K25: 211 | L25: =+GETPIVOTDATA("estimated_salary_range",$J$21,"estimated_salary_range","51,000 - 100,000")/GETPIVOTDATA("estimated_salary_range",$J$21) -> 0.26810673
J26: Grand Total | K26: 787
B30: Customers left
D32: Credit Score Quality | H32: Country | L32: Gender | P32: Age category
B33: Row Labels | C33: Count of credit_score_quality | D33: % | F33: Row Labels | G33: Count of country | H33: % | J33: Row Labels | K33: Count of gender | L33: % | N33: Row Labels | O33: Count of age_category | P33: %
B34: Fair | C34: 129 | D34: =GETPIVOTDATA("credit_score_quality",$B$33,"credit_score_quality","Fair")/GETPIVOTDATA("credit_score_quality",$B$33) -> 0.63235294 | F34: France | G34: 77 | H34: =GETPIVOTDATA("country",$F$33,"country","France")/GETPIVOTDATA("country",$F$33) -> 0.37745098 | J34: Female | K34: 121 | L34: =GETPIVOTDATA("gender",$J$33,"gender","Female")/GETPIVOTDATA("gender",$J$33) -> 0.59313725 | N34: Middle-aged adult | O34: 123 | P34: =GETPIVOTDATA("age_category",$N$33,"age_category","Middle-aged adult")/GETPIVOTDATA("age_category",$N$33) -> 0.60294118
B35: Good | C35: 47 | D35: =GETPIVOTDATA("credit_score_quality",$B$33,"credit_score_quality","Good")/GETPIVOTDATA("credit_score_quality",$B$33) -> 0.23039216 | F35: Germany | G35: 75 | H35: =GETPIVOTDATA("country",$F$33,"country","Germany")/GETPIVOTDATA("country",$F$33) -> 0.36764706 | J35: Male | K35: 83 | L35: =GETPIVOTDATA("gender",$J$33,"gender","Male")/GETPIVOTDATA("gender",$J$33) -> 0.40686275 | N35: Senior adult | O35: 21 | P35: =GETPIVOTDATA("age_category",$N$33,"age_category","Senior adult")/GETPIVOTDATA("age_category",$N$33) -> 0.10294118
B36: Poor | C36: 28 | D36: =GETPIVOTDATA("credit_score_quality",$B$33,"credit_score_quality","Poor")/GETPIVOTDATA("credit_score_quality",$B$33) -> 0.1372549 | F36: Spain | G36: 52 | H36: =GETPIVOTDATA("country",$F$33,"country","Spain")/GETPIVOTDATA("country",$F$33) -> 0.25490196 | J36: Grand Total | K36: 204 | N36: Young adult | O36: 60 | P36: =GETPIVOTDATA("age_category",$N$33,"age_category","Young adult")/GETPIVOTDATA("age_category",$N$33) -> 0.29411765
B37: Grand Total | C37: 204 | F37: Grand Total | G37: 204 | N37: Grand Total | O37: 204
D40: Tenure | H40: Balance category | L40: Number of products | P40: Has credit card?
B41: Row Labels | C41: Count of tenure | D41: % | F41: Row Labels | G41: Count of balance_category | H41: % | J41: Row Labels | K41: Count of num_of_products | L41: % | N41: Row Labels | O41: Count of has_credit_card | P41: %
B42: 0 | C42: 6 | D42: =GETPIVOTDATA("tenure",$B$41,"tenure",0)/GETPIVOTDATA("tenure",$B$41) -> 0.029411765 | F42: High-Balance | G42: 70 | H42: =GETPIVOTDATA("balance_category",$F$41,"balance_category","High-Balance")/GETPIVOTDATA("balance_category",$F$41) -> 0.34313725 | J42: 1 | K42: 142 | L42: =GETPIVOTDATA("num_of_products",$J$41,"num_of_products",1)/GETPIVOTDATA("num_of_products",$J$41) -> 0.69607843 | N42: 0 | O42: 60 | P42: =GETPIVOTDATA("has_credit_card",$N$41,"has_credit_card",0)/GETPIVOTDATA("has_credit_card",$N$41) -> 0.29411765
B43: 1 | C43: 30 | D43: =GETPIVOTDATA("tenure",$B$41,"tenure",1)/GETPIVOTDATA("tenure",$B$41) -> 0.14705882 | F43: Low-Balance | G43: 65 | H43: =GETPIVOTDATA("balance_category",$F$41,"balance_category","Low-Balance")/GETPIVOTDATA("balance_category",$F$41) -> 0.31862745 | J43: 2 | K43: 32 | L43: =GETPIVOTDATA("num_of_products",$J$41,"num_of_products",2)/GETPIVOTDATA("num_of_products",$J$41) -> 0.15686275 | N43: 1 | O43: 144 | P43: =GETPIVOTDATA("has_credit_card",$N$41,"has_credit_card",1)/GETPIVOTDATA("has_credit_card",$N$41) -> 0.70588235
B44: 2 | C44: 27 | D44: =GETPIVOTDATA("tenure",$B$41,"tenure",2)/GETPIVOTDATA("tenure",$B$41) -> 0.13235294 | F44: Mid-Balance | G44: 69 | H44: =GETPIVOTDATA("balance_category",$F$41,"balance_category","Mid-Balance")/GETPIVOTDATA("balance_category",$F$41) -> 0.33823529 | J44: 3 | K44: 28 | L44: =GETPIVOTDATA("num_of_products",$J$41,"num_of_products",3)/GETPIVOTDATA("num_of_products",$J$41) -> 0.1372549 | N44: Grand Total | O44: 204
B45: 3 | C45: 20 | D45: =GETPIVOTDATA("tenure",$B$41,"tenure",3)/GETPIVOTDATA("tenure",$B$41) -> 0.098039216 | F45: Grand Total | G45: 204 | J45: 4 | K45: 2 | L45: =GETPIVOTDATA("num_of_products",$J$41,"num_of_products",4)/GETPIVOTDATA("num_of_products",$J$41) -> 0.0098039216
B46: 4 | C46: 17 | D46: =GETPIVOTDATA("tenure",$B$41,"tenure",4)/GETPIVOTDATA("tenure",$B$41) -> 0.083333333 | J46: Grand Total | K46: 204
B47: 5 | C47: 20 | D47: =GETPIVOTDATA("tenure",$B$41,"tenure",5)/GETPIVOTDATA("tenure",$B$41) -> 0.098039216
B48: 6 | C48: 21 | D48: =GETPIVOTDATA("tenure",$B$41,"tenure",6)/GETPIVOTDATA("tenure",$B$41) -> 0.10294118 | H48: Is active member? | L48: Estimated salary range
B49: 7 | C49: 15 | D49: =GETPIVOTDATA("tenure",$B$41,"tenure",7)/GETPIVOTDATA("tenure",$B$41) -> 0.073529412 | F49: Row Labels | G49: Count of is_active_member | H49: % | J49: Row Labels | K49: Count of estimated_salary_range | L49: %
B50: 8 | C50: 20 | D50: =GETPIVOTDATA("tenure",$B$41,"tenure",8)/GETPIVOTDATA("tenure",$B$41) -> 0.098039216 | F50: 0 | G50: 143 | H50: =GETPIVOTDATA("is_active_member",$F$49,"is_active_member",0)/GETPIVOTDATA("is_active_member",$F$49) -> 0.70098039 | J50: 0 - 50,000 | K50: 58 | L50: =GETPIVOTDATA("estimated_salary_range",$J$49,"estimated_salary_range"," 0 - 50,000")/GETPIVOTDATA("estimated_salary_range",$J$49) -> 0.28431373
B51: 9 | C51: 21 | D51: =GETPIVOTDATA("tenure",$B$41,"tenure",9)/GETPIVOTDATA("tenure",$B$41) -> 0.10294118 | F51: 1 | G51: 61 | H51: =GETPIVOTDATA("is_active_member",$F$49,"is_active_member",1)/GETPIVOTDATA("is_active_member",$F$49) -> 0.29901961 | J51: 101,000 - 150,000 | K51: 56 | L51: =GETPIVOTDATA("estimated_salary_range",$J$49,"estimated_salary_range","101,000 - 150,000")/GETPIVOTDATA("estimated_salary_range",$J$49) -> 0.2745098
B52: 10 | C52: 7 | D52: =GETPIVOTDATA("tenure",$B$41,"tenure",10)/GETPIVOTDATA("tenure",$B$41) -> 0.034313725 | F52: Grand Total | G52: 204 | J52: 151,000 - 200,00 | K52: 46 | L52: =GETPIVOTDATA("estimated_salary_range",$J$49,"estimated_salary_range","151,000 - 200,00")/GETPIVOTDATA("estimated_salary_range",$J$49) -> 0.2254902
B53: Grand Total | C53: 204 | J53: 51,000 - 100,000 | K53: 44 | L53: =GETPIVOTDATA("estimated_salary_range",$J$49,"estimated_salary_range","51,000 - 100,000")/GETPIVOTDATA("estimated_salary_range",$J$49) -> 0.21568627
J54: Grand Total | K54: 204
B58: Active members
B60: Row Labels | C60: Sum of exited_from_bank | D60: Sum of exited_from_bank2
B61: Female | C61: 19 | D61: 0.79166667
B62: Middle-aged adult | C62: 14 | D62: 0.73684211
B63: 2 | C63: 7 | D63: 0.5
B64: 3 | C64: 7 | D64: 0.5
B65: Senior adult | C65: 1 | D65: 0.052631579
B66: 2 | C66: 0 | D66: 0
B67: 3 | C67: 1 | D67: 1
B68: Young adult | C68: 4 | D68: 0.21052632
B69: 2 | C69: 3 | D69: 0.75
B70: 3 | C70: 1 | D70: 0.25
B71: Male | C71: 5 | D71: 0.20833333
B72: Middle-aged adult | C72: 3 | D72: 0.6
B73: 2 | C73: 1 | D73: 0.33333333
B74: 3 | C74: 2 | D74: 0.66666667
B75: Senior adult | C75: 0 | D75: 0
B76: 2 | C76: 0
B77: Young adult | C77: 2 | D77: 0.4
B78: 2 | C78: 1 | D78: 0.5
B79: 3 | C79: 1 | D79: 0.5
B80: Grand Total | C80: 24 | D80: 1

Sheet 12 - Descriptive statistics
B2: The clients were separated into 2 groups: one for those who have left the bank and a second for those who have stayed ("ExitedFromBank" = 1 represents customers who have left).
B5: Statistical information on both groups:
B8: Cleaned Data | C8: Minimum | D8: Maximum | E8: Mean | F8: Mode
B9: credit_score | C9: 376 | D9: 850 | E9: 648.60747 | F9: -
B10: age | C10: 18 | D10: 82 | E10: 38.883956 | F10: -
B11: tenure | C11: 0 | D11: 10 | E11: 5.0665994 | F11: -
B12: balance | C12: 0 | D12: 213146.2 | E12: 78002.718 | F12: -
B13: num_of_products | C13: 1 | D13: 4 | E13: 1.5227043 | F13: -
B14: estimated_salary | C14: 371.05 | D14: 199725.39 | E14: 98555.138 | F14: -
B15: country | C15: - | D15: - | E15: - | F15: France
B16: gender | C16: - | D16: - | E16: - | F16: Male
B17: has_credit_card | C17: - | D17: - | E17: - | F17: 1
B18: is_active_member | C18: - | D18: - | E18: - | F18: 1
B20: Customers stayed | C20: Minimum | D20: Maximum | E20: Mean | F20: Mode
B21: credit_score | C21: =MIN('09 - Customers stayed'!D2:D788) -> 411 | D21: =MAX('09 - Customers stayed'!D2:D788) -> 850 | E21: =AVERAGE('09 - Customers stayed'!D2:D788) -> 651.70902 | F21: -
B22: age | C22: =MIN('09 - Customers stayed'!G2:G788) -> 18 | D22: =MAX('09 - Customers stayed'!G2:G788) -> 82 | E22: =AVERAGE('09 - Customers stayed'!G2:G788) -> 37.268107 | F22: -
B23: tenure | C23: =MIN('09 - Customers stayed'!H2:H788) -> 0 | D23: =MAX('09 - Customers stayed'!H2:H788) -> 10 | E23: =AVERAGE('09 - Customers stayed'!H2:H788) -> 5.1575604 | F23: -
B24: balance | C24: =MIN('09 - Customers stayed'!I2:I788) -> 0 | D24: =MAX('09 - Customers stayed'!I2:I788) -> 197041.8 | E24: =AVERAGE('09 - Customers stayed'!I2:I788) -> 74830.868 | F24: -
B25: num_of_products | C25: =MIN('09 - Customers stayed'!J2:J788) -> 1 | D25: =MAX('09 - Customers stayed'!J2:J788) -> 3 | E25: =AVERAGE('09 - Customers stayed'!J2:J788) -> 1.5387548 | F25: -
B26: estimated_salary | C26: =MIN('09 - Customers stayed'!M2:M788) -> 371.05 | D26: =MAX('09 - Customers stayed'!M2:M788) -> 199661.5 | E26: =AVERAGE('09 - Customers stayed'!M2:M788) -> 98918.018 | F26: -
B27: country | C27: - | D27: - | E27: - | F27: France
B28: gender | C28: - | D28: - | E28: - | F28: Male
B29: has_credit_card | C29: - | D29: - | E29: - | F29: 1
B30: is_active_member | C30: - | D30: - | E30: - | F30: 1
B32: Customers left | C32: Minimum | D32: Maximum | E32: Mean | F32: Mode
B33: credit_score | C33: =MIN('10 - Customers left'!D2:D205) -> 376 | D33: =MAX('10 - Customers left'!D2:D205) -> 850 | E33: =AVERAGE('10 - Customers left'!D2:D205) -> 636.64216 | F33: -
B34: age | C34: =MIN('10 - Customers left'!G2:G205) -> 20 | D34: =MAX('10 - Customers left'!G2:G205) -> 69 | E34: =AVERAGE('10 - Customers left'!G2:G205) -> 45.117647 | F34: -
B35: tenure | C35: =MIN('10 - Customers left'!H2:H205) -> 0 | D35: =MAX('10 - Customers left'!H2:H205) -> 10 | E35: =AVERAGE('10 - Customers left'!H2:H205) -> 4.7156863 | F35: -
B36: balance | C36: =MIN('10 - Customers left'!I2:I205) -> 0 | D36: =MAX('10 - Customers left'!I2:I205) -> 213146.2 | E36: =AVERAGE('10 - Customers left'!I2:I205) -> 90239.219 | F36: -
B37: num_of_products | C37: =MIN('10 - Customers left'!J2:J205) -> 1 | D37: =MAX('10 - Customers left'!J2:J205) -> 4 | E37: =AVERAGE('10 - Customers left'!J2:J205) -> 1.4607843 | F37: -
B38: estimated_salary | C38: =MIN('10 - Customers left'!M2:M205) -> 417.41 | D38: =MAX('10 - Customers left'!M2:M205) -> 199725.39 | E38: =AVERAGE('10 - Customers left'!M2:M205) -> 97155.205 | F38: -
B39: country | C39: - | D39: - | E39: - | F39: France
B40: gender | C40: - | D40: - | E40: - | F40: Female
B41: has_credit_card | C41: - | D41: - | E41: - | F41: 1
B42: is_active_member | C42: - | D42: - | E42: - | F42: 0
B45: Some categorization was performed to handle different variables:
B48: New variable | C48: Derived from | D48: Categorization
B49: credit_score_quality | C49: credit_score | D49: Good: 721 - 850 Fair: 521 - 720 Poor: 300 - 520
B50: age_category | C50: age | D50: Young adult: 18 - 39 Middle-aged adult: 40 - 59 Senior adult: 60 - 85
B51: balance_category | C51: balance | D51: Low-Balance: 30,000 - 75,000 Mid-Balance: 76,000 - 125,000 High-Balance: 126,000 - 200,000+
B52: estimated_salary_range | C52: estimated_salary | D52: 0 - 50, 000 51,000 - 100,000 101,000 - 150,000 151,000 - 200,000
B55: Comparison between "Customers stayed" and "Customers left" pivot tables | H55: Comments
B58: Credit Score Quality | H58: Customers who left the bank showed a slightly higher poor credit score quality and a lower good credit score quality.
C59: Customers stayed | E59: Customers feft
C60: Count of credit_score_quality | D60: Percentage of credit_score_quality | E60: Count of credit_score_quality | F60: Percentage of credit_score_quality
B61: Fair | C61: 496 | D61: 0.63024142 | E61: 129 | F61: 0.63235294
B62: Good | C62: 203 | D62: 0.25794155 | E62: 47 | F62: 0.23039216
B63: Poor | C63: 88 | D63: 0.11181703 | E63: 28 | F63: 0.1372549
B64: Grand Total | C64: 787 | D64: 1 | E64: 204 | F64: 1
B66: Country | H66: There are important geographical differences. The majority of customers who left the bank are in France. However, when calculating churn rates, Germany shows a higher churn rate (29%) than Spain (20%) and France has a lower relative risk (16%).
C67: Customers stayed | E67: Customers feft
C68: Count of country | D68: Percentage of country | E68: Count of country | F68: Percentage of country
B69: France | C69: 403 | D69: 0.51207116 | E69: 77 | F69: 0.37745098
B70: Germany | C70: 182 | D70: 0.23125794 | E70: 75 | F70: 0.36764706
B71: Spain | C71: 202 | D71: 0.2566709 | E71: 52 | F71: 0.25490196
B72: Grand Total | C72: 787 | D72: 1 | E72: 204 | F72: 1
B74: Age category | H74: 60% of customers who left the bank are middle-aged adults, whereas 68% of customers who stayed are young adults. Middle-aged adults (40–59) are much more likely to leave. Younger people tend to stay.
C75: Customers stayed | E75: Customers feft
C76: Count of age_category | D76: Percentage of age_category | E76: Count of age_category | F76: Percentage of age_category
B77: Young adult | C77: 535 | D77: 0.6797967 | E77: 60 | F77: 0.29411765
B78: Middle-aged adult | C78: 221 | D78: 0.28081321 | E78: 123 | F78: 0.60294118
B79: Senior adult | C79: 31 | D79: 0.039390089 | E79: 21 | F79: 0.10294118
B80: Grand Total | C80: 787 | D80: 1 | E80: 204 | F80: 1
B82: Gender | H82: The majority of customers who left the bank are female, while the majority of customers who stayed are male.
C83: Customers stayed | E83: Customers feft
C84: Count of gender | D84: Percentage of gender | E84: Count of gender | F84: Percentage of gender
B85: Female | C85: 341 | D85: 0.43329098 | E85: 121 | F85: 0.59313725
B86: Male | C86: 446 | D86: 0.56670902 | E86: 83 | F86: 0.40686275
B87: Grand Total | C87: 787 | D87: 1 | E87: 204 | F87: 1
B89: Tenure | H89: Tenure do not seem to be a factor for customers leaving the bank.
C90: Customers stayed | E90: Customers feft
C91: Count of tenure | D91: Percentage of tenure | E91: Count of tenure | F91: Percentage of tenure
B92: 0 | C92: 32 | D92: 0.040660737 | E92: 6 | F92: 0.029411765
B93: 1 | C93: 73 | D93: 0.092757306 | E93: 30 | F93: 0.14705882
B94: 2 | C94: 83 | D94: 0.10546379 | E94: 27 | F94: 0.13235294
B95: 3 | C95: 81 | D95: 0.10292249 | E95: 20 | F95: 0.098039216
B96: 4 | C96: 69 | D96: 0.087674714 | E96: 17 | F96: 0.083333333
B97: 5 | C97: 80 | D97: 0.10165184 | E97: 20 | F97: 0.098039216
B98: 6 | C98: 73 | D98: 0.092757306 | E98: 21 | F98: 0.10294118
B99: 7 | C99: 78 | D99: 0.099110546 | E99: 15 | F99: 0.073529412
B100: 8 | C100: 88 | D100: 0.11181703 | E100: 20 | F100: 0.098039216
B101: 9 | C101: 87 | D101: 0.11054638 | E101: 21 | F101: 0.10294118
B102: 10 | C102: 43 | D102: 0.054637865 | E102: 7 | F102: 0.034313725
B103: Grand Total | C103: 787 | D103: 1 | E103: 204 | F103: 1
B105: Number of products | H105: 70% of customers who left the bank have only 1 product, compared to 47% of those who stayed. Customers with only 1 product are much more likely to leave. Customers with 2 products are more loyal.
C106: Customers stayed | E106: Customers feft
C107: Count of num_of_products | D107: Percentage of num_of_products | E107: Count of num_of_products | F107: Percentage of num_of_products
B108: 1 | C108: 368 | D108: 0.46759848 | E108: 142 | F108: 0.69607843
B109: 2 | C109: 414 | D109: 0.52604828 | E109: 32 | F109: 0.15686275
B110: 3 | C110: 5 | D110: 0.0063532402 | E110: 28 | F110: 0.1372549
B111: 4 | C111: - | D111: - | E111: 2 | F111: 0.0098039216
B112: Grand Total | C112: 787 | D112: 1 | E112: 204 | F112: 1
B115: Has credit card? | H115: The fact that a customer has a credit card or not, do not seem to be a factor for customers leaving the bank.
C116: Customers stayed | E116: Customers feft
C117: Count of has_credit_card | D117: Percentage of has_credit_card | E117: Count of has_credit_card | F117: Percentage of has_credit_card
B118: 0 | C118: 231 | D118: 0.2935197 | E118: 60 | F118: 0.29411765
B119: 1 | C119: 556 | D119: 0.7064803 | E119: 144 | F119: 0.70588235
B120: Grand Total | C120: 787 | D120: 1 | E120: 204 | F120: 1
B123: Is active member? | H123: 70% of customers who left the bank are not active members. Inactive customers are much more likely to leave.
C124: Customers stayed | E124: Customers feft
...

Sheet 13 - Decision Tree
B2: Decision Tree to determine the probability of customers leaving the bank
B5: From the identified risk factors that have contributed to customers leaving the bank, they are now ordered in terms of impact:
B6: 1. Activity level: Inactive: 70% left
B7: 2. Number of products: 1 product: 70% left
B8: 3. Age: Middle-aged adults: 60% left
B9: 4. Country: 29% of German customers left
B11: Note: The activity level will be the top decision node with the greatest impact, because it represents the current engagement and it is simply splited in two (Active/Inactive). This current behaviour is usually more predictive. The number of products is more a historical engagement of the customer, and it can be splited in 4 options (1-4 products).
B13: For the active customers branch, data showed that age didn't matter much after the number of products, but gender instead:
B14: In active customers with 1 product, female gender has a higher risk.
B15: In active customers with 2+ products, the risk is already low, no further split needed.
B52: Business Impact
B54: The highest-risk customer profile identified was: - Inactive customer - Only one banking product - Middle-aged - Located in Germany The results indicate that customer retention is strongly influenced by engagement levels and the use of multiple products. Reducing inactivity and promoting wider product adoption are likely to play a key role in lowering customer churn.

Sheet 14 - Time Series
A1: Year | B1: Avg Oil Price | C1: 5 Yr MA | E1: Time Series Analysis
A2: 32142 | B2: 19.2
A3: 32508 | B3: 15.97 | E3: The objective of this analysis was to evaluate long-term oil price behavior. A five-year moving average (5-Year MA) was calculated to smooth short-term fluctuations and better visualize long-term market trends.
A4: 32873 | B4: 19.64
A5: 33238 | B5: 24.53
A6: 33603 | B6: 21.54
A7: 33969 | B7: 20.58 | C7: =AVERAGE(B2:B6) -> 20.176 | O7: Observations: The oil price series displayed a general upward trend over time, indicating a non-stationary time series. Prices experienced several fluctuations and volatility spikes across different years. The five-year moving average smoothed the sharp rises and drops in oil prices, making the broader trend easier to interpret. This improves forecasting by emphasizing long-term trends rather than temporary fluctuations. This helps analysts better understand macroeconomic behavior and identify more stable trend patterns for financial planning and investment analysis. Conclusion: Although oil prices fluctuate considerably in the short term, the moving average demonstrates that long-term trend analysis provides a more reliable foundation for forecasting and strategic decision-making.
A8: 34334 | B8: 18.43 | C8: =AVERAGE(B3:B7) -> 20.452
A9: 34699 | B9: 17.2 | C9: =AVERAGE(B4:B8) -> 20.944
A10: 35064 | B10: 18.43 | C10: =AVERAGE(B5:B9) -> 20.456
A11: 35430 | B11: 22.12 | C11: =AVERAGE(B6:B10) -> 19.236
A12: 35795 | B12: 20.61 | C12: =AVERAGE(B7:B11) -> 19.352
A13: 36160 | B13: 14.42 | C13: =AVERAGE(B8:B12) -> 19.358
A14: 36525 | B14: 19.35 | C14: =AVERAGE(B9:B13) -> 18.556
A15: 36891 | B15: 30.38 | C15: =AVERAGE(B10:B14) -> 18.986
A16: 37256 | B16: 25.98 | C16: =AVERAGE(B11:B15) -> 21.376
A17: 37621 | B17: 26.19 | C17: =AVERAGE(B12:B16) -> 22.148
A18: 37986 | B18: 31.08 | C18: =AVERAGE(B13:B17) -> 23.264
A19: 38352 | B19: 41.51 | C19: =AVERAGE(B14:B18) -> 26.596
... A34: 43830 | B34: 56.99 | C34: =AVERAGE(B29:B33) -> 60.23

Sheet 15 - Recommendations
B1: Customer Retention Recommendations
B3: 1. Increase Customer Engagement
B4: Develop targeted engagement campaigns for inactive customers through personalized communication, loyalty programs, and digital banking incentives.
B6: 2. Promote Multi-Product Adoption
B7: Encourage customers to adopt additional banking products, as customers with multiple products showed significantly lower churn rates.
B9: 3. Focus on High-Risk Demographics
B10: Implement retention strategies specifically designed for middle-aged customers, who demonstrated higher churn probabilities.
B12: 4. Monitor Geographic Risk Patterns
B13: Conduct deeper analysis into the higher churn rates observed in Germany to identify operational, cultural, or service-related drivers.
